{
    "status": "OK",
    "request_id": "ce0bc45a-f3ed-48ee-8784-3ce3efde5453",
    "parameters": {
        "query": "bin stores in washington",
        "language": "en",
        "region": "us",
        "lat": 37.09024,
        "lng": -95.712891,
        "zoom": 13,
        "limit": 20,
        "offset": 0,
        "extract_emails_and_contacts": true
    },
    "data": [
        {
            "business_id": "0x5490050b5e198ca1:0x1bfe6c07a6f6465",
            "google_id": "0x5490050b5e198ca1:0x1bfe6c07a6f6465",
            "place_id": "ChIJoYwZXgsFkFQRZWRvesDmvwE",
            "google_mid": "/g/11lg2_xf_5",
            "phone_number": "+14259216151",
            "name": "Cheaper by the Day",
            "latitude": 47.8202946,
            "longitude": -122.29496259999999,
            "full_address": "Cheaper by the Day, 19800 44th Ave W, Lynnwood, WA 98036",
            "review_count": 170,
            "rating": 2.8,
            "timezone": "America/Los_Angeles",
            "opening_status": "Open \u22c5 Closes 5\u202fPM",
            "working_hours": {
                "Sunday": [
                    "12\u20135 PM"
                ],
                "Monday": [
                    "10 AM\u20135 PM"
                ],
                "Tuesday": [
                    "10 AM\u20135 PM"
                ],
                "Wednesday": [
                    "10 AM\u20133 PM"
                ],
                "Thursday": [
                    "Closed"
                ],
                "Friday": [
                    "10 AM\u20136 PM"
                ],
                "Saturday": [
                    "10 AM\u20136 PM"
                ]
            },
            "website": "http://cheaperbytheday1.com",
            "verified": true,
            "place_link": "https://www.google.com/maps/place/data=!3m1!4b1!4m2!3m1!1s0x5490050b5e198ca1:0x1bfe6c07a6f6465",
            "cid": "126073028951893093",
            "reviews_link": "https://search.google.com/local/reviews?placeid=ChIJoYwZXgsFkFQRZWRvesDmvwE&q=bin+stores+in+washington&authuser=0&hl=en&gl=US",
            "owner_id": "110302070620905162701",
            "owner_link": "https://maps.google.com/maps/contrib/110302070620905162701",
            "owner_name": "Cheaper by the Day",
            "booking_link": null,
            "reservations_link": null,
            "business_status": "OPEN",
            "type": "Discount store",
            "subtypes": [
                "Discount store",
                "Home goods store"
            ],
            "photos_sample": [
                {
                    "photo_id": "AF1QipNE5EgqlAm38yQa_Bsvy9tZ621gdCV95qNcbA-I",
                    "photo_url": "https://lh5.googleusercontent.com/p/AF1QipNE5EgqlAm38yQa_Bsvy9tZ621gdCV95qNcbA-I",
                    "photo_url_large": "https://lh5.googleusercontent.com/p/AF1QipNE5EgqlAm38yQa_Bsvy9tZ621gdCV95qNcbA-I=w4032-h3024-k-no",
                    "video_thumbnail_url": null,
                    "latitude": 47.820346199999996,
                    "longitude": -122.2947218,
                    "type": "photo",
                    "photo_datetime_utc": "2020-12-04T00:00:00.000Z",
                    "photo_timestamp": 1607040000
                }
            ],
            "reviews_per_rating": null,
            "photo_count": 57,
            "about": {
                "summary": null,
                "details": {
                    "Service options": {
                        "Delivery": false,
                        "Same-day delivery": false
                    },
                    "Accessibility": {
                        "Wheelchair accessible entrance": true,
                        "Wheelchair accessible parking lot": true
                    },
                    "Payments": {
                        "Credit cards": true,
                        "Debit cards": true,
                        "NFC mobile payments": true
                    }
                }
            },
            "address": "19800 44th Ave W, Lynnwood, WA 98036",
            "order_link": null,
            "price_level": null,
            "district": null,
            "street_address": "19800 44th Ave W",
            "city": "Lynnwood",
            "zipcode": "98036",
            "state": "Washington",
            "country": "US",
            "emails_and_contacts": {
                "emails": [],
                "phone_numbers": [
                    "2099630649220"
                ],
                "facebook": "https://www.facebook.com/CheaperbytheDay",
                "instagram": "https://www.instagram.com/shopcheaperbytheday",
                "yelp": null,
                "tiktok": "https://www.tiktok.com/@cheaperbytheday",
                "snapchat": null,
                "twitter": null,
                "linkedin": null,
                "github": null,
                "youtube": null,
                "pinterest": null
            },
            "no": 98
        },
        {
            "business_id": "0x54915f9cc7b130d3:0x28d202699c0e1135",
            "google_id": "0x54915f9cc7b130d3:0x28d202699c0e1135",
            "place_id": "ChIJ0zCxx5xfkVQRNREOnGkC0ig",
            "google_mid": "/g/11sw0bq1_0",
            "phone_number": null,
            "name": "AMZing Outlet Liquidation & Bin Store",
            "latitude": 46.717349399999996,
            "longitude": -122.9540488,
            "full_address": "AMZing Outlet Liquidation & Bin Store, 203 N Tower Ave, Centralia, WA 98531",
            "review_count": 87,
            "rating": 4.8,
            "timezone": "America/Los_Angeles",
            "opening_status": "Closed \u22c5 Opens 10\u202fAM Tue",
            "working_hours": {
                "Sunday": [
                    "Closed"
                ],
                "Monday": [
                    "Closed"
                ],
                "Tuesday": [
                    "10 AM\u20136 PM"
                ],
                "Wednesday": [
                    "10 AM\u20136 PM"
                ],
                "Thursday": [
                    "10 AM\u20136 PM"
                ],
                "Friday": [
                    "10 AM\u20136 PM"
                ],
                "Saturday": [
                    "10 AM\u20136 PM"
                ]
            },
            "website": "https://linktr.ee/amzingoutlet",
            "verified": true,
            "place_link": "https://www.google.com/maps/place/data=!3m1!4b1!4m2!3m1!1s0x54915f9cc7b130d3:0x28d202699c0e1135",
            "cid": "2941416159239344437",
            "reviews_link": "https://search.google.com/local/reviews?placeid=ChIJ0zCxx5xfkVQRNREOnGkC0ig&q=bin+stores+in+washington&authuser=0&hl=en&gl=US",
            "owner_id": "116052067993968881025",
            "owner_link": "https://maps.google.com/maps/contrib/116052067993968881025",
            "owner_name": "AMZing Outlet Liquidation & Bin Store",
            "booking_link": null,
            "reservations_link": null,
            "business_status": "OPEN",
            "type": "Liquidator",
            "subtypes": [
                "Liquidator"
            ],
            "photos_sample": [
                {
                    "photo_id": "AF1QipPN04fMRx34RjpqvRaqWTDJQR9z3sMX7hJpEcmH",
                    "photo_url": "https://lh5.googleusercontent.com/p/AF1QipPN04fMRx34RjpqvRaqWTDJQR9z3sMX7hJpEcmH",
                    "photo_url_large": "https://lh5.googleusercontent.com/p/AF1QipPN04fMRx34RjpqvRaqWTDJQR9z3sMX7hJpEcmH=w4032-h3024-k-no",
                    "video_thumbnail_url": null,
                    "latitude": 46.7173102,
                    "longitude": -122.95387160000001,
                    "type": "photo",
                    "photo_datetime_utc": "2023-08-15T00:00:00.000Z",
                    "photo_timestamp": 1692057600
                }
            ],
            "reviews_per_rating": null,
            "photo_count": 89,
            "about": {
                "summary": null,
                "details": {
                    "From the business": {
                        "Identifies as veteran-owned": true,
                        "Identifies as women-owned": true
                    },
                    "Accessibility": {
                        "Wheelchair accessible entrance": true,
                        "Wheelchair accessible parking lot": true,
                        "Wheelchair accessible restroom": true
                    },
                    "Amenities": {
                        "Gender-neutral restroom": true
                    }
                }
            },
            "address": "203 N Tower Ave, Centralia, WA 98531",
            "order_link": null,
            "price_level": null,
            "district": null,
            "street_address": "203 N Tower Ave",
            "city": "Centralia",
            "zipcode": "98531",
            "state": "Washington",
            "country": "US",
            "emails_and_contacts": {
                "emails": [],
                "phone_numbers": [],
                "facebook": null,
                "instagram": null,
                "yelp": null,
                "tiktok": null,
                "snapchat": null,
                "twitter": null,
                "linkedin": null,
                "github": null,
                "youtube": null,
                "pinterest": null
            },
            "no": 98
        },
        {
            "business_id": "0x5490575e71f9a8e3:0xc4c9205d5059131e",
            "google_id": "0x5490575e71f9a8e3:0xc4c9205d5059131e",
            "place_id": "ChIJ46j5cV5XkFQRHhNZUF0gycQ",
            "google_mid": "/g/11t5nsc811",
            "phone_number": "+12063315113",
            "name": "Save By The Day",
            "latitude": 47.3130004,
            "longitude": -122.30951719999999,
            "full_address": "Save By The Day, 1901 S Commons, Mall Entrance, Federal Way, WA 98003",
            "review_count": 71,
            "rating": 3.5,
            "timezone": "America/Los_Angeles",
            "opening_status": "Open \u22c5 Closes 5\u202fPM",
            "working_hours": {
                "Sunday": [
                    "11 AM\u20135 PM"
                ],
                "Monday": [
                    "10 AM\u20137 PM"
                ],
                "Tuesday": [
                    "10 AM\u20137 PM"
                ],
                "Wednesday": [
                    "10 AM\u20137 PM"
                ],
                "Thursday": [
                    "10 AM\u20137 PM"
                ],
                "Friday": [
                    "Closed"
                ],
                "Saturday": [
                    "10 AM\u20137 PM"
                ]
            },
            "website": "https://www.facebook.com/Save-By-The-Day-Bin-Store-104578165578076",
            "verified": true,
            "place_link": "https://www.google.com/maps/place/data=!3m1!4b1!4m2!3m1!1s0x5490575e71f9a8e3:0xc4c9205d5059131e",
            "cid": "14179900486904779550",
            "reviews_link": "https://search.google.com/local/reviews?placeid=ChIJ46j5cV5XkFQRHhNZUF0gycQ&q=bin+stores+in+washington&authuser=0&hl=en&gl=US",
            "owner_id": "116791717548833953409",
            "owner_link": "https://maps.google.com/maps/contrib/116791717548833953409",
            "owner_name": "Save By The Day",
            "booking_link": null,
            "reservations_link": null,
            "business_status": "OPEN",
            "type": "Liquidator",
            "subtypes": [
                "Liquidator"
            ],
            "photos_sample": [
                {
                    "photo_id": "AF1QipO2bCusLGQIomFhLcBMgxIdwnu50bOh08e7HUnW",
                    "photo_url": "https://lh5.googleusercontent.com/p/AF1QipO2bCusLGQIomFhLcBMgxIdwnu50bOh08e7HUnW",
                    "photo_url_large": "https://lh5.googleusercontent.com/p/AF1QipO2bCusLGQIomFhLcBMgxIdwnu50bOh08e7HUnW=w4032-h3024-k-no",
                    "video_thumbnail_url": null,
                    "latitude": 47.3123265,
                    "longitude": -122.30953389999999,
                    "type": "photo",
                    "photo_datetime_utc": "2022-07-30T00:00:00.000Z",
                    "photo_timestamp": 1659139200
                }
            ],
            "reviews_per_rating": null,
            "photo_count": 119,
            "about": {
                "summary": null,
                "details": {
                    "Service options": {
                        "Onsite services": true
                    },
                    "Accessibility": {
                        "Wheelchair accessible entrance": true,
                        "Wheelchair accessible parking lot": true
                    }
                }
            },
            "address": "1901 S Commons, Mall Entrance, Federal Way, WA 98003",
            "order_link": null,
            "price_level": null,
            "district": null,
            "street_address": "1901 S Commons, Mall Entrance",
            "city": "Federal Way",
            "zipcode": "98003",
            "state": "WA",
            "country": "US",
            "emails_and_contacts": {
                "emails": [],
                "phone_numbers": [],
                "facebook": null,
                "instagram": null,
                "yelp": null,
                "tiktok": null,
                "snapchat": null,
                "twitter": null,
                "linkedin": null,
                "github": null,
                "youtube": null,
                "pinterest": null
            },
            "no": 98
        },
        {
            "business_id": "0x549e19a7784c045d:0x8bff4a0c4824b7a8",
            "google_id": "0x549e19a7784c045d:0x8bff4a0c4824b7a8",
            "place_id": "ChIJXQRMeKcZnlQRqLckSAxK_4s",
            "google_mid": "/g/11rnk7hsg8",
            "phone_number": "+15093158283",
            "name": "Spokane Bins",
            "latitude": 47.6568557,
            "longitude": -117.3328581,
            "full_address": "Spokane Bins, 5320 E Sprague Ave, Spokane Valley, WA 99212",
            "review_count": 124,
            "rating": 4,
            "timezone": "America/Los_Angeles",
            "opening_status": "Open \u22c5 Closes 6\u202fPM",
            "working_hours": {
                "Sunday": [
                    "10 AM\u20136 PM"
                ],
                "Monday": [
                    "10 AM\u20136 PM"
                ],
                "Tuesday": [
                    "10 AM\u20136 PM"
                ],
                "Wednesday": [
                    "10 AM\u20134 PM"
                ],
                "Thursday": [
                    "Closed"
                ],
                "Friday": [
                    "Closed"
                ],
                "Saturday": [
                    "10 AM\u20136 PM"
                ]
            },
            "website": null,
            "verified": true,
            "place_link": "https://www.google.com/maps/place/data=!3m1!4b1!4m2!3m1!1s0x549e19a7784c045d:0x8bff4a0c4824b7a8",
            "cid": "10087863106943629224",
            "reviews_link": "https://search.google.com/local/reviews?placeid=ChIJXQRMeKcZnlQRqLckSAxK_4s&q=bin+stores+in+washington&authuser=0&hl=en&gl=US",
            "owner_id": "110874214600863424150",
            "owner_link": "https://maps.google.com/maps/contrib/110874214600863424150",
            "owner_name": "Spokane Bins",
            "booking_link": null,
            "reservations_link": null,
            "business_status": "OPEN",
            "type": "Discount store",
            "subtypes": [
                "Discount store"
            ],
            "photos_sample": [
                {
                    "photo_id": "AF1QipMK4G5IHMixczxMiieCpvODedDk42_uiWk9O7H7",
                    "photo_url": "https://lh5.googleusercontent.com/p/AF1QipMK4G5IHMixczxMiieCpvODedDk42_uiWk9O7H7",
                    "photo_url_large": "https://lh5.googleusercontent.com/p/AF1QipMK4G5IHMixczxMiieCpvODedDk42_uiWk9O7H7=w3024-h4032-k-no",
                    "video_thumbnail_url": null,
                    "latitude": 47.6569885,
                    "longitude": -117.33285120000001,
                    "type": "photo",
                    "photo_datetime_utc": "2022-05-01T00:00:00.000Z",
                    "photo_timestamp": 1651363200
                }
            ],
            "reviews_per_rating": null,
            "photo_count": 4,
            "about": {
                "summary": null,
                "details": {
                    "From the business": {
                        "Small business": true
                    },
                    "Service options": {
                        "In-store shopping": true,
                        "Delivery": false,
                        "Same-day delivery": false
                    },
                    "Accessibility": {
                        "Wheelchair accessible entrance": true,
                        "Wheelchair accessible parking lot": true
                    },
                    "Payments": {
                        "Credit cards": true,
                        "Debit cards": true
                    }
                }
            },
            "address": "5320 E Sprague Ave, Spokane Valley, WA 99212",
            "order_link": null,
            "price_level": null,
            "district": null,
            "street_address": "5320 E Sprague Ave",
            "city": "Spokane Valley",
            "zipcode": "99212",
            "state": "Washington",
            "country": "US",
            "emails_and_contacts": {
                "emails": [],
                "phone_numbers": [],
                "facebook": null,
                "instagram": null,
                "yelp": null,
                "tiktok": null,
                "snapchat": null,
                "twitter": null,
                "linkedin": null,
                "github": null,
                "youtube": null,
                "pinterest": null
            },
            "no": 98
        },
        {
            "business_id": "0x80ca5bcbf2475c65:0x7926e2bb82d4477c",
            "google_id": "0x80ca5bcbf2475c65:0x7926e2bb82d4477c",
            "place_id": "ChIJZVxH8stbyoARfEfUgrviJnk",
            "google_mid": "/g/11jsf4lysc",
            "phone_number": "+14356806680",
            "name": "Southern Utah Bargain Bin",
            "latitude": 37.129399899999996,
            "longitude": -113.5184773,
            "full_address": "Southern Utah Bargain Bin, 520 W Telegraph St #3, Washington, UT 84780",
            "review_count": 25,
            "rating": 5,
            "timezone": "America/Denver",
            "opening_status": "Closed \u22c5 Opens 10\u202fAM Thu",
            "working_hours": {
                "Sunday": [
                    "Closed"
                ],
                "Monday": [
                    "Closed"
                ],
                "Tuesday": [
                    "Closed"
                ],
                "Wednesday": [
                    "Closed"
                ],
                "Thursday": [
                    "10 AM\u20138 PM"
                ],
                "Friday": [
                    "10 AM\u20138 PM"
                ],
                "Saturday": [
                    "10 AM\u20138 PM"
                ]
            },
            "website": "https://www.southernutbargainbin.com",
            "verified": true,
            "place_link": "https://www.google.com/maps/place/data=!3m1!4b1!4m2!3m1!1s0x80ca5bcbf2475c65:0x7926e2bb82d4477c",
            "cid": "8729914222685996924",
            "reviews_link": "https://search.google.com/local/reviews?placeid=ChIJZVxH8stbyoARfEfUgrviJnk&q=bin+stores+in+washington&authuser=0&hl=en&gl=US",
            "owner_id": "101741293685929067383",
            "owner_link": "https://maps.google.com/maps/contrib/101741293685929067383",
            "owner_name": "Southern Utah Bargain Bin",
            "booking_link": null,
            "reservations_link": null,
            "business_status": "OPEN",
            "type": "Discount store",
            "subtypes": [
                "Discount store"
            ],
            "photos_sample": [
                {
                    "photo_id": "AF1QipNigXuQ829uQykIXVFQHXCjlVwRjW2qHOT9ZtjO",
                    "photo_url": "https://lh5.googleusercontent.com/p/AF1QipNigXuQ829uQykIXVFQHXCjlVwRjW2qHOT9ZtjO",
                    "photo_url_large": "https://lh5.googleusercontent.com/p/AF1QipNigXuQ829uQykIXVFQHXCjlVwRjW2qHOT9ZtjO=w1700-h1254-k-no",
                    "video_thumbnail_url": null,
                    "latitude": 37.1295687,
                    "longitude": -113.5184611,
                    "type": "photo",
                    "photo_datetime_utc": "2023-02-10T00:00:00.000Z",
                    "photo_timestamp": 1675987200
                }
            ],
            "reviews_per_rating": null,
            "photo_count": 4,
            "about": {
                "summary": null,
                "details": {
                    "From the business": {
                        "Identifies as women-owned": true,
                        "Small business": true
                    },
                    "Service options": {
                        "In-store pickup": true,
                        "In-store shopping": true,
                        "Delivery": false,
                        "Same-day delivery": false
                    },
                    "Accessibility": {
                        "Wheelchair accessible entrance": true,
                        "Wheelchair accessible parking lot": true
                    },
                    "Planning": {
                        "Quick visit": true
                    },
                    "Payments": {
                        "Credit cards": true,
                        "Debit cards": true
                    }
                }
            },
            "address": "520 W Telegraph St #3, Washington, UT 84780",
            "order_link": null,
            "price_level": null,
            "district": null,
            "street_address": "520 W Telegraph St #3",
            "city": "Washington",
            "zipcode": "84780",
            "state": "Utah",
            "country": "US",
            "emails_and_contacts": {
                "emails": [],
                "phone_numbers": [],
                "facebook": "https://www.facebook.com/Southernutbargainbin",
                "instagram": "https://www.instagram.com/southernutbargainbin",
                "yelp": null,
                "tiktok": "https://www.tiktok.com/@southernutbargainbin",
                "snapchat": null,
                "twitter": null,
                "linkedin": null,
                "github": null,
                "youtube": null,
                "pinterest": null
            },
            "no": 98
        },
        {
            "business_id": "0x548fb30869ba39d5:0x10ba7b70767c54b3",
            "google_id": "0x548fb30869ba39d5:0x10ba7b70767c54b3",
            "place_id": "ChIJ1Tm6aQizj1QRs1R8dnB7uhA",
            "google_mid": "/g/11w2qh6qch",
            "phone_number": "+15094289473",
            "name": "10 to 1 bins llc",
            "latitude": 48.102393199999995,
            "longitude": -123.50323089999999,
            "full_address": "10 to 1 bins llc, 2450 US-101, Port Angeles, WA 98363",
            "review_count": 2,
            "rating": 5,
            "timezone": "America/Los_Angeles",
            "opening_status": "Open \u22c5 Closes 3\u202fPM",
            "working_hours": {
                "Sunday": [
                    "10 AM\u20133 PM"
                ],
                "Monday": [
                    "10 AM\u20133 PM"
                ],
                "Tuesday": [
                    "10 AM\u20133 PM"
                ],
                "Wednesday": [
                    "Closed"
                ],
                "Thursday": [
                    "Closed"
                ],
                "Friday": [
                    "10 AM\u20133 PM"
                ],
                "Saturday": [
                    "10 AM\u20133 PM"
                ]
            },
            "website": null,
            "verified": true,
            "place_link": "https://www.google.com/maps/place/data=!3m1!4b1!4m2!3m1!1s0x548fb30869ba39d5:0x10ba7b70767c54b3",
            "cid": "1205411573229442227",
            "reviews_link": "https://search.google.com/local/reviews?placeid=ChIJ1Tm6aQizj1QRs1R8dnB7uhA&q=bin+stores+in+washington&authuser=0&hl=en&gl=US",
            "owner_id": "108025338990808680916",
            "owner_link": "https://maps.google.com/maps/contrib/108025338990808680916",
            "owner_name": "10 to 1 bins llc",
            "booking_link": null,
            "reservations_link": null,
            "business_status": "OPEN",
            "type": "Discount store",
            "subtypes": [
                "Discount store"
            ],
            "photos_sample": [
                {
                    "photo_id": "AF1QipOyS5nzU6OlWx8ifJws8GM5pU4Y5CMEvHbpmK4B",
                    "photo_url": "https://lh5.googleusercontent.com/p/AF1QipOyS5nzU6OlWx8ifJws8GM5pU4Y5CMEvHbpmK4B",
                    "photo_url_large": "https://lh5.googleusercontent.com/p/AF1QipOyS5nzU6OlWx8ifJws8GM5pU4Y5CMEvHbpmK4B=w3024-h4032-k-no",
                    "video_thumbnail_url": null,
                    "latitude": 48.1025433,
                    "longitude": -123.5032274,
                    "type": "photo",
                    "photo_datetime_utc": "2024-08-22T00:00:00.000Z",
                    "photo_timestamp": 1724284800
                }
            ],
            "reviews_per_rating": null,
            "photo_count": 4,
            "about": {
                "summary": null,
                "details": {
                    "Service options": {
                        "Delivery": false,
                        "Same-day delivery": false
                    },
                    "Accessibility": {
                        "Wheelchair accessible parking lot": true
                    },
                    "Payments": {
                        "Credit cards": true
                    }
                }
            },
            "address": "2450 US-101, Port Angeles, WA 98363",
            "order_link": null,
            "price_level": null,
            "district": null,
            "street_address": "2450 US-101",
            "city": "Port Angeles",
            "zipcode": "98363",
            "state": "Washington",
            "country": "US",
            "emails_and_contacts": {
                "emails": [],
                "phone_numbers": [],
                "facebook": null,
                "instagram": null,
                "yelp": null,
                "tiktok": null,
                "snapchat": null,
                "twitter": null,
                "linkedin": null,
                "github": null,
                "youtube": null,
                "pinterest": null
            },
            "no": 98
        },
        {
            "business_id": "0x5490554e3309aeb7:0xa1b4ef27c9155133",
            "google_id": "0x5490554e3309aeb7:0xa1b4ef27c9155133",
            "place_id": "ChIJt64JM05VkFQRM1EVySfvtKE",
            "google_mid": "/g/11b5zy_99_",
            "phone_number": "+12535736720",
            "name": "Tacoma Goodwill Outlet",
            "latitude": 47.2314845,
            "longitude": -122.4738591,
            "full_address": "Tacoma Goodwill Outlet, 3120 S Pine St, Tacoma, WA 98409",
            "review_count": 715,
            "rating": 3.9,
            "timezone": "America/Los_Angeles",
            "opening_status": "Open \u22c5 Closes 6\u202fPM",
            "working_hours": {
                "Sunday": [
                    "9 AM\u20136 PM"
                ],
                "Monday": [
                    "9 AM\u20136 PM"
                ],
                "Tuesday": [
                    "9 AM\u20136 PM"
                ],
                "Wednesday": [
                    "9 AM\u20136 PM"
                ],
                "Thursday": [
                    "9 AM\u20136 PM"
                ],
                "Friday": [
                    "9 AM\u20136 PM"
                ],
                "Saturday": [
                    "9 AM\u20136 PM"
                ]
            },
            "website": "http://www.goodwillwa.org",
            "verified": true,
            "place_link": "https://www.google.com/maps/place/data=!3m1!4b1!4m2!3m1!1s0x5490554e3309aeb7:0xa1b4ef27c9155133",
            "cid": "11652201090070696243",
            "reviews_link": "https://search.google.com/local/reviews?placeid=ChIJt64JM05VkFQRM1EVySfvtKE&q=bin+stores+in+washington&authuser=0&hl=en&gl=US",
            "owner_id": "117885004889668255399",
            "owner_link": "https://maps.google.com/maps/contrib/117885004889668255399",
            "owner_name": "Tacoma Goodwill Outlet",
            "booking_link": null,
            "reservations_link": null,
            "business_status": "OPEN",
            "type": "Thrift store",
            "subtypes": [
                "Thrift store",
                "Store"
            ],
            "photos_sample": [
                {
                    "photo_id": "AF1QipOoSOtcIt4A8XZ57-3R2_4LiYLMnQzvGI80HOyq",
                    "photo_url": "https://lh5.googleusercontent.com/p/AF1QipOoSOtcIt4A8XZ57-3R2_4LiYLMnQzvGI80HOyq",
                    "photo_url_large": "https://lh5.googleusercontent.com/p/AF1QipOoSOtcIt4A8XZ57-3R2_4LiYLMnQzvGI80HOyq=w4032-h2674-k-no",
                    "video_thumbnail_url": null,
                    "latitude": 47.2309263,
                    "longitude": -122.475208,
                    "type": "photo",
                    "photo_datetime_utc": "2020-01-16T00:00:00.000Z",
                    "photo_timestamp": 1579132800
                }
            ],
            "reviews_per_rating": null,
            "photo_count": 266,
            "about": {
                "summary": "Long-standing nonprofit chain with a range of pre-owned clothing, housewares & more.",
                "details": {
                    "Service options": {
                        "In-store shopping": true,
                        "Delivery": false,
                        "Same-day delivery": false
                    },
                    "Accessibility": {
                        "Wheelchair accessible entrance": true,
                        "Wheelchair accessible parking lot": true
                    },
                    "Planning": {
                        "Quick visit": true
                    },
                    "Recycling": {
                        "Clothing": true
                    },
                    "Payments": {
                        "Credit cards": true,
                        "Debit cards": true,
                        "NFC mobile payments": true
                    }
                }
            },
            "address": "3120 S Pine St, Tacoma, WA 98409",
            "order_link": null,
            "price_level": null,
            "district": "South Tacoma",
            "street_address": "3120 S Pine St",
            "city": "Tacoma",
            "zipcode": "98409",
            "state": "Washington",
            "country": "US",
            "emails_and_contacts": {
                "emails": [
                    "careerhub@goodwillwa.org",
                    "grow@goodwillwa.org"
                ],
                "phone_numbers": [
                    "2535736508",
                    "2533483882"
                ],
                "facebook": "https://www.facebook.com/goodwillwa",
                "instagram": "https://www.instagram.com/wagoodwill",
                "yelp": "https://www.yelp.com/biz/goodwill-tacoma",
                "tiktok": null,
                "snapchat": null,
                "twitter": "https://twitter.com/goodwillwa",
                "linkedin": null,
                "github": null,
                "youtube": "https://www.youtube.com/c/GoodwilloftheOlympicsandRainierRegion",
                "pinterest": "https://www.pinterest.com/goodwillwa"
            },
            "no": 98
        },
        {
            "business_id": "0x87b7135b4f5e418b:0x155b630e5072dd76",
            "google_id": "0x87b7135b4f5e418b:0x155b630e5072dd76",
            "place_id": "ChIJi0FeT1sTt4cRdt1yUA5jWxU",
            "google_mid": "/g/11s1933gc6",
            "phone_number": null,
            "name": "$5 Gold Diggers Bin Store",
            "latitude": 36.7493122,
            "longitude": -95.93270799999999,
            "full_address": "$5 Gold Diggers Bin Store, 520 SE Washington Blvd, Bartlesville, OK 74006",
            "review_count": 57,
            "rating": 4.5,
            "timezone": "America/Chicago",
            "opening_status": "Open \u22c5 Closes 5\u202fPM",
            "working_hours": {
                "Sunday": [
                    "1\u20135 PM"
                ],
                "Monday": [
                    "11 AM\u20137 PM"
                ],
                "Tuesday": [
                    "11 AM\u20137 PM"
                ],
                "Wednesday": [
                    "Closed"
                ],
                "Thursday": [
                    "Closed"
                ],
                "Friday": [
                    "Closed"
                ],
                "Saturday": [
                    "10 AM\u20136 PM"
                ]
            },
            "website": null,
            "verified": false,
            "place_link": "https://www.google.com/maps/place/data=!3m1!4b1!4m2!3m1!1s0x87b7135b4f5e418b:0x155b630e5072dd76",
            "cid": "1538932610807553398",
            "reviews_link": "https://search.google.com/local/reviews?placeid=ChIJi0FeT1sTt4cRdt1yUA5jWxU&q=bin+stores+in+washington&authuser=0&hl=en&gl=US",
            "owner_id": "100778017243362430477",
            "owner_link": "https://maps.google.com/maps/contrib/100778017243362430477",
            "owner_name": "$5 Gold Diggers Bin Store",
            "booking_link": null,
            "reservations_link": null,
            "business_status": "OPEN",
            "type": "General store",
            "subtypes": [
                "General store",
                "Market"
            ],
            "photos_sample": [
                {
                    "photo_id": "AF1QipPGYTv1qcWZLN20mHzKHgCDEqqDbjGDhFcZs-IR",
                    "photo_url": "https://lh5.googleusercontent.com/p/AF1QipPGYTv1qcWZLN20mHzKHgCDEqqDbjGDhFcZs-IR",
                    "photo_url_large": "https://lh5.googleusercontent.com/p/AF1QipPGYTv1qcWZLN20mHzKHgCDEqqDbjGDhFcZs-IR=w2322-h4128-k-no",
                    "video_thumbnail_url": null,
                    "latitude": 36.74930483230874,
                    "longitude": -95.93270803572632,
                    "type": "photo",
                    "photo_datetime_utc": "2021-12-14T00:00:00.000Z",
                    "photo_timestamp": 1639440000
                }
            ],
            "reviews_per_rating": null,
            "photo_count": 2,
            "about": {
                "summary": null,
                "details": {
                    "Service options": {
                        "Delivery": false,
                        "Same-day delivery": false
                    },
                    "Accessibility": {
                        "Wheelchair accessible entrance": true,
                        "Wheelchair accessible parking lot": true
                    },
                    "Planning": {
                        "Quick visit": true
                    },
                    "Payments": {
                        "Credit cards": true
                    }
                }
            },
            "address": "520 SE Washington Blvd, Bartlesville, OK 74006",
            "order_link": null,
            "price_level": null,
            "district": null,
            "street_address": "520 SE Washington Blvd",
            "city": "Bartlesville",
            "zipcode": "74006",
            "state": "Oklahoma",
            "country": "US",
            "emails_and_contacts": {
                "emails": [],
                "phone_numbers": [],
                "facebook": null,
                "instagram": null,
                "yelp": null,
                "tiktok": null,
                "snapchat": null,
                "twitter": null,
                "linkedin": null,
                "github": null,
                "youtube": null,
                "pinterest": null
            },
            "no": 98
        },
        {
            "business_id": "0x549101c222b7d30b:0x4c99ca6ada2a6ff",
            "google_id": "0x549101c222b7d30b:0x4c99ca6ada2a6ff",
            "place_id": "ChIJC9O3IsIBkVQR_6airaacyQQ",
            "google_mid": "/g/1thkwzw1",
            "phone_number": "+12535371107",
            "name": "Valley Liquidation",
            "latitude": 47.1679363,
            "longitude": -122.4337082,
            "full_address": "Valley Liquidation, 9813 Pacific Ave S, Tacoma, WA 98444",
            "review_count": 1436,
            "rating": 4.6,
            "timezone": "America/Los_Angeles",
            "opening_status": "Open \u22c5 Closes 7:30\u202fPM",
            "working_hours": {
                "Sunday": [
                    "8 AM\u20137:30 PM"
                ],
                "Monday": [
                    "8 AM\u20137:30 PM"
                ],
                "Tuesday": [
                    "8 AM\u20137:30 PM"
                ],
                "Wednesday": [
                    "8 AM\u20137:30 PM"
                ],
                "Thursday": [
                    "8 AM\u20137:30 PM"
                ],
                "Friday": [
                    "8 AM\u20137:30 PM"
                ],
                "Saturday": [
                    "8 AM\u20137:30 PM"
                ]
            },
            "website": null,
            "verified": true,
            "place_link": "https://www.google.com/maps/place/data=!3m1!4b1!4m2!3m1!1s0x549101c222b7d30b:0x4c99ca6ada2a6ff",
            "cid": "344979086162175743",
            "reviews_link": "https://search.google.com/local/reviews?placeid=ChIJC9O3IsIBkVQR_6airaacyQQ&q=bin+stores+in+washington&authuser=0&hl=en&gl=US",
            "owner_id": "116106381653077293115",
            "owner_link": "https://maps.google.com/maps/contrib/116106381653077293115",
            "owner_name": "Valley Liquidation",
            "booking_link": null,
            "reservations_link": null,
            "business_status": "OPEN",
            "type": "Grocery store",
            "subtypes": [
                "Grocery store"
            ],
            "photos_sample": [
                {
                    "photo_id": "AF1QipMt_urfOGYQJlrK-v8n5SwMss6SKq8ipfvy_q6Y",
                    "photo_url": "https://lh5.googleusercontent.com/p/AF1QipMt_urfOGYQJlrK-v8n5SwMss6SKq8ipfvy_q6Y",
                    "photo_url_large": "https://lh5.googleusercontent.com/p/AF1QipMt_urfOGYQJlrK-v8n5SwMss6SKq8ipfvy_q6Y=w4032-h2268-k-no",
                    "video_thumbnail_url": null,
                    "latitude": 47.16793627471556,
                    "longitude": -122.43370819997837,
                    "type": "photo",
                    "photo_datetime_utc": "2017-07-23T00:00:00.000Z",
                    "photo_timestamp": 1500768000
                }
            ],
            "reviews_per_rating": null,
            "photo_count": 483,
            "about": {
                "summary": "This no-frills discount retailer offers fresh fruits & vegetables, groceries & other items.",
                "details": {
                    "From the business": {
                        "Small business": true
                    },
                    "Service options": {
                        "In-store shopping": true,
                        "Delivery": false,
                        "Same-day delivery": false
                    },
                    "Highlights": {
                        "Great produce": true
                    },
                    "Accessibility": {
                        "Wheelchair accessible entrance": true,
                        "Wheelchair accessible parking lot": true
                    },
                    "Planning": {
                        "Quick visit": true
                    },
                    "Payments": {
                        "Credit cards": true,
                        "Debit cards": true,
                        "NFC mobile payments": true,
                        "SNAP/EBT": true
                    }
                }
            },
            "address": "9813 Pacific Ave S, Tacoma, WA 98444",
            "order_link": null,
            "price_level": null,
            "district": null,
            "street_address": "9813 Pacific Ave S",
            "city": "Tacoma",
            "zipcode": "98444",
            "state": "Washington",
            "country": "US",
            "emails_and_contacts": {
                "emails": [],
                "phone_numbers": [],
                "facebook": null,
                "instagram": null,
                "yelp": null,
                "tiktok": null,
                "snapchat": null,
                "twitter": null,
                "linkedin": null,
                "github": null,
                "youtube": null,
                "pinterest": null
            },
            "no": 98
        },
        {
            "business_id": "0x54900140652d0847:0x9d11981650228959",
            "google_id": "0x54900140652d0847:0x9d11981650228959",
            "place_id": "ChIJRwgtZUABkFQRWYkiUBaYEZ0",
            "google_mid": "/g/1tdb8jqq",
            "phone_number": "+14252638540",
            "name": "Everett Outlet Goodwill",
            "latitude": 47.9190113,
            "longitude": -122.26333109999999,
            "full_address": "Everett Outlet Goodwill, 2208 W Casino Rd, Everett, WA 98204",
            "review_count": 404,
            "rating": 4,
            "timezone": "America/Los_Angeles",
            "opening_status": "Open \u22c5 Closes 6\u202fPM",
            "working_hours": {
                "Sunday": [
                    "9 AM\u20136 PM"
                ],
                "Monday": [
                    "9 AM\u20136 PM"
                ],
                "Tuesday": [
                    "9 AM\u20136 PM"
                ],
                "Wednesday": [
                    "9 AM\u20136 PM"
                ],
                "Thursday": [
                    "9 AM\u20136 PM"
                ],
                "Friday": [
                    "9 AM\u20136 PM"
                ],
                "Saturday": [
                    "9 AM\u20136 PM"
                ]
            },
            "website": "https://evergreengoodwill.org/locations/8-everett-outlet",
            "verified": true,
            "place_link": "https://www.google.com/maps/place/data=!3m1!4b1!4m2!3m1!1s0x54900140652d0847:0x9d11981650228959",
            "cid": "11317994560159910233",
            "reviews_link": "https://search.google.com/local/reviews?placeid=ChIJRwgtZUABkFQRWYkiUBaYEZ0&q=bin+stores+in+washington&authuser=0&hl=en&gl=US",
            "owner_id": "117050841402985880436",
            "owner_link": "https://maps.google.com/maps/contrib/117050841402985880436",
            "owner_name": "Everett Outlet Goodwill",
            "booking_link": null,
            "reservations_link": null,
            "business_status": "OPEN",
            "type": "Thrift store",
            "subtypes": [
                "Thrift store",
                "Non-profit organization"
            ],
            "photos_sample": [
                {
                    "photo_id": "AF1QipN-gLVFCdPU94ImjKbettFcbbtew1VOr5mD3sqB",
                    "photo_url": "https://lh5.googleusercontent.com/p/AF1QipN-gLVFCdPU94ImjKbettFcbbtew1VOr5mD3sqB",
                    "photo_url_large": "https://lh5.googleusercontent.com/p/AF1QipN-gLVFCdPU94ImjKbettFcbbtew1VOr5mD3sqB=w4032-h3024-k-no",
                    "video_thumbnail_url": null,
                    "latitude": 47.919011329739114,
                    "longitude": -122.26333111962643,
                    "type": "photo",
                    "photo_datetime_utc": "2017-05-26T00:00:00.000Z",
                    "photo_timestamp": 1495756800
                }
            ],
            "reviews_per_rating": null,
            "photo_count": 78,
            "about": {
                "summary": "Long-standing nonprofit chain with a range of pre-owned clothing, housewares & more.",
                "details": {
                    "Service options": {
                        "In-store shopping": true,
                        "Online estimates": false,
                        "Delivery": false,
                        "Onsite services": false,
                        "Same-day delivery": false
                    },
                    "Accessibility": {
                        "Wheelchair accessible entrance": true,
                        "Wheelchair accessible parking lot": true
                    },
                    "Recycling": {
                        "Clothing": true,
                        "Electronics": true
                    },
                    "Payments": {
                        "Credit cards": true,
                        "Debit cards": true,
                        "NFC mobile payments": true
                    }
                }
            },
            "address": "2208 W Casino Rd, Everett, WA 98204",
            "order_link": null,
            "price_level": null,
            "district": "Westmont",
            "street_address": "2208 W Casino Rd",
            "city": "Everett",
            "zipcode": "98204",
            "state": "Washington",
            "country": "US",
            "emails_and_contacts": {
                "emails": [],
                "phone_numbers": [],
                "facebook": null,
                "instagram": null,
                "yelp": null,
                "tiktok": null,
                "snapchat": null,
                "twitter": null,
                "linkedin": null,
                "github": null,
                "youtube": null,
                "pinterest": null
            },
            "no": 98
        },
        {
            "business_id": "0x54987f71c4639a5b:0xd68f7e8bad18abee",
            "google_id": "0x54987f71c4639a5b:0xd68f7e8bad18abee",
            "place_id": "ChIJW5pjxHF_mFQR7qsYrYt-j9Y",
            "google_mid": "/g/11t88jm926",
            "phone_number": null,
            "name": "Hot Deals Liquidation",
            "latitude": 46.224113599999995,
            "longitude": -119.1019998,
            "full_address": "Hot Deals Liquidation, 1124 W Ainsworth St E, Pasco, WA 99301",
            "review_count": 76,
            "rating": 4,
            "timezone": "America/Los_Angeles",
            "opening_status": "Open \u22c5 Closes 5\u202fPM",
            "working_hours": {
                "Sunday": [
                    "10 AM\u20135 PM"
                ],
                "Monday": [
                    "9 AM\u20137 PM"
                ],
                "Tuesday": [
                    "9 AM\u20137 PM"
                ],
                "Wednesday": [
                    "9 AM\u20137 PM"
                ],
                "Thursday": [
                    "Closed"
                ],
                "Friday": [
                    "9 AM\u20137 PM"
                ],
                "Saturday": [
                    "9 AM\u20136 PM"
                ]
            },
            "website": "https://m.facebook.com/110708855043301",
            "verified": false,
            "place_link": "https://www.google.com/maps/place/data=!3m1!4b1!4m2!3m1!1s0x54987f71c4639a5b:0xd68f7e8bad18abee",
            "cid": "15460715184155831278",
            "reviews_link": "https://search.google.com/local/reviews?placeid=ChIJW5pjxHF_mFQR7qsYrYt-j9Y&q=bin+stores+in+washington&authuser=0&hl=en&gl=US",
            "owner_id": "113313491677245329681",
            "owner_link": "https://maps.google.com/maps/contrib/113313491677245329681",
            "owner_name": "Hot Deals Liquidation",
            "booking_link": null,
            "reservations_link": null,
            "business_status": "OPEN",
            "type": "Outlet store",
            "subtypes": [
                "Outlet store"
            ],
            "photos_sample": [
                {
                    "photo_id": "AF1QipMRENvK09pnX_vtY7EIoQG5Mndyy5CDo1lJESoj",
                    "photo_url": "https://lh5.googleusercontent.com/p/AF1QipMRENvK09pnX_vtY7EIoQG5Mndyy5CDo1lJESoj",
                    "photo_url_large": "https://lh5.googleusercontent.com/p/AF1QipMRENvK09pnX_vtY7EIoQG5Mndyy5CDo1lJESoj=w1816-h4032-k-no",
                    "video_thumbnail_url": null,
                    "latitude": 46.2243022,
                    "longitude": -119.1019805,
                    "type": "photo",
                    "photo_datetime_utc": "2023-01-27T00:00:00.000Z",
                    "photo_timestamp": 1674777600
                }
            ],
            "reviews_per_rating": null,
            "photo_count": 45,
            "about": {
                "summary": null,
                "details": {
                    "Service options": {
                        "Delivery": false,
                        "Same-day delivery": false
                    },
                    "Accessibility": {
                        "Wheelchair accessible entrance": true,
                        "Wheelchair accessible parking lot": true
                    },
                    "Planning": {
                        "Quick visit": true
                    },
                    "Payments": {
                        "Credit cards": true,
                        "Debit cards": true,
                        "NFC mobile payments": true
                    }
                }
            },
            "address": "1124 W Ainsworth St E, Pasco, WA 99301",
            "order_link": null,
            "price_level": null,
            "district": null,
            "street_address": "1124 W Ainsworth St E",
            "city": "Pasco",
            "zipcode": "99301",
            "state": "Washington",
            "country": "US",
            "emails_and_contacts": {
                "emails": [],
                "phone_numbers": [],
                "facebook": null,
                "instagram": null,
                "yelp": null,
                "tiktok": null,
                "snapchat": null,
                "twitter": null,
                "linkedin": null,
                "github": null,
                "youtube": null,
                "pinterest": null
            },
            "no": 98
        },
        {
            "business_id": "0x54910b303dac28bb:0xec42a6a3850f27c6",
            "google_id": "0x54910b303dac28bb:0xec42a6a3850f27c6",
            "place_id": "ChIJuyisPTALkVQRxicPhaOmQuw",
            "google_mid": "/g/11b75jhbt_",
            "phone_number": "+13604562484",
            "name": "Olympia Goodwill Outlet",
            "latitude": 47.048413599999996,
            "longitude": -122.8358854,
            "full_address": "Olympia Goodwill Outlet, 4014 Martin Way E, Olympia, WA 98506",
            "review_count": 415,
            "rating": 3.8,
            "timezone": "America/Los_Angeles",
            "opening_status": "Open \u22c5 Closes 6\u202fPM",
            "working_hours": {
                "Sunday": [
                    "9 AM\u20136 PM"
                ],
                "Monday": [
                    "9 AM\u20136 PM"
                ],
                "Tuesday": [
                    "9 AM\u20136 PM"
                ],
                "Wednesday": [
                    "9 AM\u20136 PM"
                ],
                "Thursday": [
                    "9 AM\u20136 PM"
                ],
                "Friday": [
                    "9 AM\u20136 PM"
                ],
                "Saturday": [
                    "9 AM\u20136 PM"
                ]
            },
            "website": "https://www.goodwillwa.org",
            "verified": true,
            "place_link": "https://www.google.com/maps/place/data=!3m1!4b1!4m2!3m1!1s0x54910b303dac28bb:0xec42a6a3850f27c6",
            "cid": "17024352762656139206",
            "reviews_link": "https://search.google.com/local/reviews?placeid=ChIJuyisPTALkVQRxicPhaOmQuw&q=bin+stores+in+washington&authuser=0&hl=en&gl=US",
            "owner_id": "107190617897876690396",
            "owner_link": "https://maps.google.com/maps/contrib/107190617897876690396",
            "owner_name": "Olympia Goodwill Outlet",
            "booking_link": null,
            "reservations_link": null,
            "business_status": "OPEN",
            "type": "Thrift store",
            "subtypes": [
                "Thrift store"
            ],
            "photos_sample": [
                {
                    "photo_id": "AF1QipOxBCX6jaOgCUDNpTW7p9ruNKC8pTLjFjEkhZLt",
                    "photo_url": "https://lh5.googleusercontent.com/p/AF1QipOxBCX6jaOgCUDNpTW7p9ruNKC8pTLjFjEkhZLt",
                    "photo_url_large": "https://lh5.googleusercontent.com/p/AF1QipOxBCX6jaOgCUDNpTW7p9ruNKC8pTLjFjEkhZLt=w4032-h3024-k-no",
                    "video_thumbnail_url": null,
                    "latitude": 47.048162999999995,
                    "longitude": -122.83568319999999,
                    "type": "photo",
                    "photo_datetime_utc": "2017-01-01T00:00:00.000Z",
                    "photo_timestamp": 1483228800
                }
            ],
            "reviews_per_rating": null,
            "photo_count": 69,
            "about": {
                "summary": "Long-standing nonprofit chain with a range of pre-owned clothing, housewares & more.",
                "details": {
                    "Service options": {
                        "In-store shopping": true,
                        "Onsite services": true,
                        "Delivery": false,
                        "Same-day delivery": false
                    },
                    "Accessibility": {
                        "Wheelchair accessible entrance": true,
                        "Wheelchair accessible parking lot": true
                    },
                    "Planning": {
                        "Quick visit": true
                    },
                    "Recycling": {
                        "Clothing": true
                    },
                    "Payments": {
                        "Credit cards": true,
                        "Debit cards": true,
                        "NFC mobile payments": true
                    }
                }
            },
            "address": "4014 Martin Way E, Olympia, WA 98506",
            "order_link": null,
            "price_level": null,
            "district": null,
            "street_address": "4014 Martin Way E",
            "city": "Olympia",
            "zipcode": "98506",
            "state": "Washington",
            "country": "US",
            "emails_and_contacts": {
                "emails": [
                    "careerhub@goodwillwa.org",
                    "grow@goodwillwa.org"
                ],
                "phone_numbers": [
                    "2535736508",
                    "2533483882"
                ],
                "facebook": "https://www.facebook.com/goodwillwa",
                "instagram": "https://www.instagram.com/wagoodwill",
                "yelp": "https://www.yelp.com/biz/goodwill-thrift-store-tacoma",
                "tiktok": null,
                "snapchat": null,
                "twitter": "https://twitter.com/goodwillwa",
                "linkedin": "https://www.linkedin.com/company/goodwilloftheolympicsandrainier",
                "github": null,
                "youtube": "https://www.youtube.com/c/GoodwilloftheOlympicsandRainierRegion",
                "pinterest": "https://www.pinterest.com/goodwillwa"
            },
            "no": 98
        },
        {
            "business_id": "0x549106919dd35dc1:0x820b0042dd1919c7",
            "google_id": "0x549106919dd35dc1:0x820b0042dd1919c7",
            "place_id": "ChIJwV3TnZEGkVQRxxkZ3UIAC4I",
            "google_mid": "/g/1tfdyk69",
            "phone_number": "+12533013816",
            "name": "92Yankee Military, Tactical & Outdoor",
            "latitude": 47.1231805,
            "longitude": -122.55166609999999,
            "full_address": "92Yankee Military, Tactical & Outdoor, 14818 Union Ave SW, Lakewood, WA 98498",
            "review_count": 224,
            "rating": 4.4,
            "timezone": "America/Los_Angeles",
            "opening_status": "Open \u22c5 Closes 5\u202fPM",
            "working_hours": {
                "Sunday": [
                    "10 AM\u20135 PM"
                ],
                "Monday": [
                    "9 AM\u20137 PM"
                ],
                "Tuesday": [
                    "9 AM\u20137 PM"
                ],
                "Wednesday": [
                    "9 AM\u20137 PM"
                ],
                "Thursday": [
                    "9 AM\u20137 PM"
                ],
                "Friday": [
                    "9 AM\u20137 PM"
                ],
                "Saturday": [
                    "10 AM\u20135 PM"
                ]
            },
            "website": "http://www.92yankee.net",
            "verified": true,
            "place_link": "https://www.google.com/maps/place/data=!3m1!4b1!4m2!3m1!1s0x549106919dd35dc1:0x820b0042dd1919c7",
            "cid": "9370583736851700167",
            "reviews_link": "https://search.google.com/local/reviews?placeid=ChIJwV3TnZEGkVQRxxkZ3UIAC4I&q=bin+stores+in+washington&authuser=0&hl=en&gl=US",
            "owner_id": "110280139219617810216",
            "owner_link": "https://maps.google.com/maps/contrib/110280139219617810216",
            "owner_name": "92Yankee Military, Tactical & Outdoor",
            "booking_link": null,
            "reservations_link": null,
            "business_status": "OPEN",
            "type": "Army & navy surplus shop",
            "subtypes": [
                "Army & navy surplus shop",
                "Boot store",
                "Camping store",
                "Police supply store",
                "Sporting goods store",
                "Surplus store",
                "Uniform store"
            ],
            "photos_sample": [
                {
                    "photo_id": "AF1QipMmMd9aBxc9GcGgj33LHGPAqkGi9st3qDpRrV87",
                    "photo_url": "https://lh5.googleusercontent.com/p/AF1QipMmMd9aBxc9GcGgj33LHGPAqkGi9st3qDpRrV87",
                    "photo_url_large": "https://lh5.googleusercontent.com/p/AF1QipMmMd9aBxc9GcGgj33LHGPAqkGi9st3qDpRrV87=w800-h600-k-no",
                    "video_thumbnail_url": null,
                    "latitude": 47.122974899999996,
                    "longitude": -122.55185029999998,
                    "type": "photo",
                    "photo_datetime_utc": "2015-03-10T00:00:00.000Z",
                    "photo_timestamp": 1425945600
                }
            ],
            "reviews_per_rating": null,
            "photo_count": 95,
            "about": {
                "summary": "Large store carrying knives, fatigues & gear for military servicepeople, police & EMTs.",
                "details": {
                    "From the business": {
                        "Small business": true
                    },
                    "Service options": {
                        "Curbside pickup": true,
                        "In-store pickup": true,
                        "In-store shopping": true,
                        "Same-day delivery": false
                    },
                    "Accessibility": {
                        "Wheelchair accessible entrance": true,
                        "Wheelchair accessible parking lot": true
                    },
                    "Planning": {
                        "Quick visit": true
                    },
                    "Payments": {
                        "Credit cards": true,
                        "Debit cards": true,
                        "NFC mobile payments": true
                    }
                }
            },
            "address": "14818 Union Ave SW, Lakewood, WA 98498",
            "order_link": null,
            "price_level": null,
            "district": null,
            "street_address": "14818 Union Ave SW",
            "city": "Lakewood",
            "zipcode": "98498",
            "state": "Washington",
            "country": "US",
            "emails_and_contacts": {
                "emails": [],
                "phone_numbers": [],
                "facebook": "https://www.facebook.com/92YankeeMilitary",
                "instagram": "https://www.instagram.com/92yankee",
                "yelp": "https://www.yelp.com/biz/92-yankee-military-tactical-and-outdoor-lakewood",
                "tiktok": null,
                "snapchat": null,
                "twitter": "https://twitter.com/92ymilitary",
                "linkedin": null,
                "github": null,
                "youtube": null,
                "pinterest": null
            },
            "no": 98
        },
        {
            "business_id": "0x5499d7ef73307955:0x59a0b54d21335a82",
            "google_id": "0x5499d7ef73307955:0x59a0b54d21335a82",
            "place_id": "ChIJVXkwc-_XmVQRglozIU21oFk",
            "google_mid": "/g/11rzth_dsg",
            "phone_number": "+15092259721",
            "name": "Los Bros Liquidation LLC",
            "latitude": 46.557660899999995,
            "longitude": -120.4757554,
            "full_address": "Los Bros Liquidation LLC, 3008 Main St Suite 100, Union Gap, WA 98903",
            "review_count": 109,
            "rating": 3.9,
            "timezone": "America/Los_Angeles",
            "opening_status": "Open \u22c5 Closes 4\u202fPM",
            "working_hours": {
                "Sunday": [
                    "9 AM\u20134 PM"
                ],
                "Monday": [
                    "9 AM\u20137 PM"
                ],
                "Tuesday": [
                    "9 AM\u20137 PM"
                ],
                "Wednesday": [
                    "9 AM\u20134 PM"
                ],
                "Thursday": [
                    "9 AM\u20137 PM"
                ],
                "Friday": [
                    "9 AM\u20137 PM"
                ],
                "Saturday": [
                    "9 AM\u20137 PM"
                ]
            },
            "website": "https://www.facebook.com/losbrosliquidation1",
            "verified": true,
            "place_link": "https://www.google.com/maps/place/data=!3m1!4b1!4m2!3m1!1s0x5499d7ef73307955:0x59a0b54d21335a82",
            "cid": "6458361208523414146",
            "reviews_link": "https://search.google.com/local/reviews?placeid=ChIJVXkwc-_XmVQRglozIU21oFk&q=bin+stores+in+washington&authuser=0&hl=en&gl=US",
            "owner_id": "110795965797009899880",
            "owner_link": "https://maps.google.com/maps/contrib/110795965797009899880",
            "owner_name": "Los Bros Liquidation LLC",
            "booking_link": null,
            "reservations_link": null,
            "business_status": "OPEN",
            "type": "Outlet store",
            "subtypes": [
                "Outlet store"
            ],
            "photos_sample": [
                {
                    "photo_id": "AF1QipPQdLnrtRuhCj5OyrXF4UpC9btMLobFwVO8HK9h",
                    "photo_url": "https://lh5.googleusercontent.com/p/AF1QipPQdLnrtRuhCj5OyrXF4UpC9btMLobFwVO8HK9h",
                    "photo_url_large": "https://lh5.googleusercontent.com/p/AF1QipPQdLnrtRuhCj5OyrXF4UpC9btMLobFwVO8HK9h=w4608-h2184-k-no",
                    "video_thumbnail_url": null,
                    "latitude": 46.5576352,
                    "longitude": -120.4755891,
                    "type": "photo",
                    "photo_datetime_utc": "2023-01-17T00:00:00.000Z",
                    "photo_timestamp": 1673913600
                }
            ],
            "reviews_per_rating": null,
            "photo_count": 3,
            "about": {
                "summary": null,
                "details": {
                    "From the business": {
                        "Small business": true
                    },
                    "Service options": {
                        "Delivery": false,
                        "Same-day delivery": false
                    },
                    "Accessibility": {
                        "Wheelchair accessible entrance": true,
                        "Wheelchair accessible parking lot": true
                    },
                    "Planning": {
                        "Quick visit": true
                    },
                    "Payments": {
                        "Credit cards": true,
                        "Debit cards": true,
                        "NFC mobile payments": true
                    }
                }
            },
            "address": "3008 Main St Suite 100, Union Gap, WA 98903",
            "order_link": null,
            "price_level": null,
            "district": null,
            "street_address": "3008 Main St Suite 100",
            "city": "Union Gap",
            "zipcode": "98903",
            "state": "Washington",
            "country": "US",
            "emails_and_contacts": {
                "emails": [],
                "phone_numbers": [],
                "facebook": null,
                "instagram": null,
                "yelp": null,
                "tiktok": null,
                "snapchat": null,
                "twitter": null,
                "linkedin": null,
                "github": null,
                "youtube": null,
                "pinterest": null
            },
            "no": 98
        },
        {
            "business_id": "0x54906a9c0ef79aeb:0xc8e61c8366ffdae",
            "google_id": "0x54906a9c0ef79aeb:0xc8e61c8366ffdae",
            "place_id": "ChIJ65r3DpxqkFQRrv1vNshhjgw",
            "google_mid": "/g/1tf9mz2s",
            "phone_number": "+12069575516",
            "name": "Seattle Outlet Goodwill",
            "latitude": 47.587364,
            "longitude": -122.3268962,
            "full_address": "Seattle Outlet Goodwill, 1765 6th Ave S, Seattle, WA 98134",
            "review_count": 457,
            "rating": 3.7,
            "timezone": "America/Los_Angeles",
            "opening_status": "Open \u22c5 Closes 5\u202fPM",
            "working_hours": {
                "Sunday": [
                    "8 AM\u20135 PM"
                ],
                "Monday": [
                    "8 AM\u20135 PM"
                ],
                "Tuesday": [
                    "8 AM\u20135 PM"
                ],
                "Wednesday": [
                    "8 AM\u20135 PM"
                ],
                "Thursday": [
                    "8 AM\u20135 PM"
                ],
                "Friday": [
                    "8 AM\u20135 PM"
                ],
                "Saturday": [
                    "8 AM\u20135 PM"
                ]
            },
            "website": "https://evergreengoodwill.org/locations/16-seattle-outlet",
            "verified": true,
            "place_link": "https://www.google.com/maps/place/data=!3m1!4b1!4m2!3m1!1s0x54906a9c0ef79aeb:0xc8e61c8366ffdae",
            "cid": "904768087682710958",
            "reviews_link": "https://search.google.com/local/reviews?placeid=ChIJ65r3DpxqkFQRrv1vNshhjgw&q=bin+stores+in+washington&authuser=0&hl=en&gl=US",
            "owner_id": "101400970507956991867",
            "owner_link": "https://maps.google.com/maps/contrib/101400970507956991867",
            "owner_name": "Seattle Outlet Goodwill",
            "booking_link": null,
            "reservations_link": null,
            "business_status": "OPEN",
            "type": "Thrift store",
            "subtypes": [
                "Thrift store",
                "Non-profit organization"
            ],
            "photos_sample": [
                {
                    "photo_id": "AF1QipMLSh1R2x1PRaUN67VrZujuCzKowo0zayMQ85Xm",
                    "photo_url": "https://lh5.googleusercontent.com/p/AF1QipMLSh1R2x1PRaUN67VrZujuCzKowo0zayMQ85Xm",
                    "photo_url_large": "https://lh5.googleusercontent.com/p/AF1QipMLSh1R2x1PRaUN67VrZujuCzKowo0zayMQ85Xm=w4000-h2992-k-no",
                    "video_thumbnail_url": null,
                    "latitude": 47.58736398593469,
                    "longitude": -122.32689622566744,
                    "type": "photo",
                    "photo_datetime_utc": "2016-08-25T00:00:00.000Z",
                    "photo_timestamp": 1472083200
                }
            ],
            "reviews_per_rating": null,
            "photo_count": 263,
            "about": {
                "summary": "Long-standing nonprofit chain with a range of pre-owned clothing, housewares & more.",
                "details": {
                    "Service options": {
                        "In-store shopping": true,
                        "Online estimates": false,
                        "Delivery": false,
                        "Onsite services": false,
                        "Same-day delivery": false
                    },
                    "Accessibility": {
                        "Wheelchair accessible entrance": true,
                        "Wheelchair accessible parking lot": true
                    },
                    "Planning": {
                        "Quick visit": true
                    },
                    "Recycling": {
                        "Clothing": true,
                        "Electronics": true
                    },
                    "Payments": {
                        "Credit cards": true,
                        "Debit cards": true,
                        "NFC mobile payments": true
                    }
                }
            },
            "address": "1765 6th Ave S, Seattle, WA 98134",
            "order_link": null,
            "price_level": null,
            "district": "SODO",
            "street_address": "1765 6th Ave S",
            "city": "Seattle",
            "zipcode": "98134",
            "state": "Washington",
            "country": "US",
            "emails_and_contacts": {
                "emails": [],
                "phone_numbers": [],
                "facebook": null,
                "instagram": null,
                "yelp": null,
                "tiktok": null,
                "snapchat": null,
                "twitter": null,
                "linkedin": null,
                "github": null,
                "youtube": null,
                "pinterest": null
            },
            "no": 98
        },
        {
            "business_id": "0x54977d26a3d0ba43:0x58e130fb4176a2e4",
            "google_id": "0x54977d26a3d0ba43:0x58e130fb4176a2e4",
            "place_id": "ChIJQ7rQoyZ9l1QR5KJ2Qfsw4Vg",
            "google_mid": "/g/11kb3tl8ms",
            "phone_number": "+15099021220",
            "name": "First Choice Liquidation",
            "latitude": 46.5462333,
            "longitude": -120.4763835,
            "full_address": "First Choice Liquidation, 4110 Main St, Union Gap, WA 98903",
            "review_count": 28,
            "rating": 3.8,
            "timezone": "America/Los_Angeles",
            "opening_status": "Open \u22c5 Closes 4\u202fPM",
            "working_hours": {
                "Sunday": [
                    "9 AM\u20134 PM"
                ],
                "Monday": [
                    "9 AM\u20136 PM"
                ],
                "Tuesday": [
                    "9 AM\u20136 PM"
                ],
                "Wednesday": [
                    "9 AM\u20136 PM"
                ],
                "Thursday": [
                    "9 AM\u20133 PM"
                ],
                "Friday": [
                    "9 AM\u20136 PM"
                ],
                "Saturday": [
                    "9 AM\u20135 PM"
                ]
            },
            "website": null,
            "verified": true,
            "place_link": "https://www.google.com/maps/place/data=!3m1!4b1!4m2!3m1!1s0x54977d26a3d0ba43:0x58e130fb4176a2e4",
            "cid": "6404454000790774500",
            "reviews_link": "https://search.google.com/local/reviews?placeid=ChIJQ7rQoyZ9l1QR5KJ2Qfsw4Vg&q=bin+stores+in+washington&authuser=0&hl=en&gl=US",
            "owner_id": "113378814709089246191",
            "owner_link": "https://maps.google.com/maps/contrib/113378814709089246191",
            "owner_name": "First Choice Liquidation",
            "booking_link": null,
            "reservations_link": null,
            "business_status": "OPEN",
            "type": "Discount store",
            "subtypes": [
                "Discount store"
            ],
            "photos_sample": [
                {
                    "photo_id": "AF1QipOxPrezsUel7MjpMPKeGJnMhvQjzzAc0q2yguoe",
                    "photo_url": "https://lh5.googleusercontent.com/p/AF1QipOxPrezsUel7MjpMPKeGJnMhvQjzzAc0q2yguoe",
                    "photo_url_large": "https://lh5.googleusercontent.com/p/AF1QipOxPrezsUel7MjpMPKeGJnMhvQjzzAc0q2yguoe=w3024-h4032-k-no",
                    "video_thumbnail_url": null,
                    "latitude": 46.5463409,
                    "longitude": -120.47595100000001,
                    "type": "photo",
                    "photo_datetime_utc": "2023-03-12T00:00:00.000Z",
                    "photo_timestamp": 1678579200
                }
            ],
            "reviews_per_rating": null,
            "photo_count": 4,
            "about": {
                "summary": null,
                "details": {
                    "From the business": {
                        "Small business": true
                    },
                    "Service options": {
                        "Delivery": true,
                        "In-store shopping": true,
                        "Same-day delivery": false
                    },
                    "Accessibility": {
                        "Wheelchair accessible entrance": true,
                        "Wheelchair accessible parking lot": true
                    },
                    "Planning": {
                        "Quick visit": true
                    },
                    "Payments": {
                        "Credit cards": true,
                        "Debit cards": true,
                        "NFC mobile payments": true
                    }
                }
            },
            "address": "4110 Main St, Union Gap, WA 98903",
            "order_link": null,
            "price_level": null,
            "district": null,
            "street_address": "4110 Main St",
            "city": "Union Gap",
            "zipcode": "98903",
            "state": "Washington",
            "country": "US",
            "emails_and_contacts": {
                "emails": [],
                "phone_numbers": [],
                "facebook": null,
                "instagram": null,
                "yelp": null,
                "tiktok": null,
                "snapchat": null,
                "twitter": null,
                "linkedin": null,
                "github": null,
                "youtube": null,
                "pinterest": null
            },
            "no": 98
        },
        {
            "business_id": "0x549aa7b48e2c1c3f:0xd43c34dedeb7ae8",
            "google_id": "0x549aa7b48e2c1c3f:0xd43c34dedeb7ae8",
            "place_id": "ChIJPxwsjrSnmlQR6Hrr7U3DQw0",
            "google_mid": "/g/1pw3yn3gc",
            "phone_number": "+13608636105",
            "name": "Big Box Outlet Store - Monroe",
            "latitude": 47.8649972,
            "longitude": -122.00582709999999,
            "full_address": "Big Box Outlet Store - Monroe, 16761 146th St SE #189, Monroe, WA 98272",
            "review_count": 560,
            "rating": 4,
            "timezone": "America/Los_Angeles",
            "opening_status": "Open \u22c5 Closes 6\u202fPM",
            "working_hours": {
                "Sunday": [
                    "10 AM\u20136 PM"
                ],
                "Monday": [
                    "10 AM\u20136 PM"
                ],
                "Tuesday": [
                    "10 AM\u20136 PM"
                ],
                "Wednesday": [
                    "10 AM\u20136 PM"
                ],
                "Thursday": [
                    "10 AM\u20136 PM"
                ],
                "Friday": [
                    "10 AM\u20136 PM"
                ],
                "Saturday": [
                    "10 AM\u20136 PM"
                ]
            },
            "website": "http://bigboxoutletstore.com",
            "verified": true,
            "place_link": "https://www.google.com/maps/place/data=!3m1!4b1!4m2!3m1!1s0x549aa7b48e2c1c3f:0xd43c34dedeb7ae8",
            "cid": "955822285404207848",
            "reviews_link": "https://search.google.com/local/reviews?placeid=ChIJPxwsjrSnmlQR6Hrr7U3DQw0&q=bin+stores+in+washington&authuser=0&hl=en&gl=US",
            "owner_id": "105472657687693865433",
            "owner_link": "https://maps.google.com/maps/contrib/105472657687693865433",
            "owner_name": "Big Box Outlet Store - Monroe",
            "booking_link": null,
            "reservations_link": null,
            "business_status": "OPEN",
            "type": "Discount store",
            "subtypes": [
                "Discount store",
                "Clothing store",
                "Outlet store",
                "Furniture store",
                "Grocery store",
                "Hardware store",
                "Home goods store",
                "Home improvement store",
                "Pet store",
                "Shoe store"
            ],
            "photos_sample": [
                {
                    "photo_id": "AF1QipN0Um-C93vEi19IhHIqQ79DrCHxS_XbZKrb5Hc",
                    "photo_url": "https://lh5.googleusercontent.com/p/AF1QipN0Um-C93vEi19IhHIqQ79DrCHxS_XbZKrb5Hc",
                    "photo_url_large": "https://lh5.googleusercontent.com/p/AF1QipN0Um-C93vEi19IhHIqQ79DrCHxS_XbZKrb5Hc=w4032-h3024-k-no",
                    "video_thumbnail_url": null,
                    "latitude": 47.864938670961934,
                    "longitude": -122.00583299187775,
                    "type": "photo",
                    "photo_datetime_utc": "2022-02-18T00:00:00.000Z",
                    "photo_timestamp": 1645142400
                }
            ],
            "reviews_per_rating": null,
            "photo_count": 88,
            "about": {
                "summary": null,
                "details": {
                    "Service options": {
                        "Delivery": true,
                        "In-store pickup": true,
                        "In-store shopping": true,
                        "Same-day delivery": false
                    },
                    "Accessibility": {
                        "Wheelchair accessible entrance": true,
                        "Wheelchair accessible parking lot": true
                    },
                    "Planning": {
                        "Quick visit": true
                    },
                    "Payments": {
                        "Credit cards": true,
                        "Debit cards": true,
                        "NFC mobile payments": true
                    }
                }
            },
            "address": "16761 146th St SE #189, Monroe, WA 98272",
            "order_link": null,
            "price_level": null,
            "district": null,
            "street_address": "16761 146th St SE #189",
            "city": "Monroe",
            "zipcode": "98272",
            "state": "Washington",
            "country": "US",
            "emails_and_contacts": {
                "emails": [],
                "phone_numbers": [
                    "13608636105"
                ],
                "facebook": "https://www.facebook.com/Mt.VernonBigBoxOutletStore",
                "instagram": null,
                "yelp": "https://www.yelp.com/biz/big-box-outlet-store-monroe",
                "tiktok": null,
                "snapchat": null,
                "twitter": null,
                "linkedin": "https://www.linkedin.com/company/big-box-outlet-store",
                "github": null,
                "youtube": "https://www.youtube.com/channel/UCc49tHqOoZqRs8NNOUswBAA",
                "pinterest": "https://www.pinterest.com/bigboxoutletstore"
            },
            "no": 98
        },
        {
            "business_id": "0x5490475133e3b01b:0x6faef2408d799f6a",
            "google_id": "0x5490475133e3b01b:0x6faef2408d799f6a",
            "place_id": "ChIJG7DjM1FHkFQRap95jUDyrm8",
            "google_mid": "/g/11kkjtrq99",
            "phone_number": "+15094968065",
            "name": "Litte Bear Bins",
            "latitude": 47.688022,
            "longitude": -122.7327136,
            "full_address": null,
            "review_count": 0,
            "rating": null,
            "timezone": "America/Los_Angeles",
            "opening_status": "Open \u22c5 Closes 9\u202fPM",
            "working_hours": {
                "Sunday": [
                    "9 AM\u20139 PM"
                ],
                "Monday": [
                    "9 AM\u20139 PM"
                ],
                "Tuesday": [
                    "Closed"
                ],
                "Wednesday": [
                    "Closed"
                ],
                "Thursday": [
                    "9 AM\u20139 PM"
                ],
                "Friday": [
                    "9 AM\u20139 PM"
                ],
                "Saturday": [
                    "9 AM\u20139 PM"
                ]
            },
            "website": null,
            "verified": true,
            "place_link": "https://www.google.com/maps/place/data=!3m1!4b1!4m2!3m1!1s0x5490475133e3b01b:0x6faef2408d799f6a",
            "cid": "8047635943223041898",
            "reviews_link": null,
            "owner_id": "116314289332258245360",
            "owner_link": "https://maps.google.com/maps/contrib/116314289332258245360",
            "owner_name": "Litte Bear Bins",
            "booking_link": null,
            "reservations_link": null,
            "business_status": "OPEN",
            "type": "Children's store",
            "subtypes": [
                "Children's store",
                "Service establishment"
            ],
            "photos_sample": [
                {
                    "photo_id": "AF1QipNDymKeM6oDB59fpqbxTbfeOjaKqYEy0Zu2Dm4D",
                    "photo_url": "https://lh5.googleusercontent.com/p/AF1QipNDymKeM6oDB59fpqbxTbfeOjaKqYEy0Zu2Dm4D",
                    "photo_url_large": "https://lh5.googleusercontent.com/p/AF1QipNDymKeM6oDB59fpqbxTbfeOjaKqYEy0Zu2Dm4D=w2784-h3880-k-no",
                    "video_thumbnail_url": null,
                    "latitude": null,
                    "longitude": null,
                    "type": "photo",
                    "photo_datetime_utc": "2020-10-18T00:00:00.000Z",
                    "photo_timestamp": 1602979200
                }
            ],
            "reviews_per_rating": null,
            "photo_count": 4,
            "about": {
                "summary": null,
                "details": {
                    "Payments": {
                        "Credit cards": true
                    }
                }
            },
            "address": null,
            "order_link": null,
            "price_level": null,
            "district": null,
            "street_address": null,
            "city": null,
            "zipcode": null,
            "state": null,
            "country": null,
            "emails_and_contacts": {
                "emails": [],
                "phone_numbers": [],
                "facebook": null,
                "instagram": null,
                "yelp": null,
                "tiktok": null,
                "snapchat": null,
                "twitter": null,
                "linkedin": null,
                "github": null,
                "youtube": null,
                "pinterest": null
            },
            "no": 98
        },
        {
            "business_id": "0x5495b049bfccfb07:0xa736faba05d98cff",
            "google_id": "0x5495b049bfccfb07:0xa736faba05d98cff",
            "place_id": "ChIJB_vMv0mwlVQR_4zZBbr6Nqc",
            "google_mid": "/g/1v4psqb5",
            "phone_number": "+13608234360",
            "name": "Goodwill Industries of the Columbia Willamette",
            "latitude": 45.6876919,
            "longitude": -122.55088289999999,
            "full_address": "Goodwill Industries of the Columbia Willamette, 9025 NE 117th Ave, Vancouver, WA 98662",
            "review_count": 465,
            "rating": 3.9,
            "timezone": "America/Los_Angeles",
            "opening_status": "Open \u22c5 Closes 7\u202fPM",
            "working_hours": {
                "Sunday": [
                    "8 AM\u20137 PM"
                ],
                "Monday": [
                    "8 AM\u20137 PM"
                ],
                "Tuesday": [
                    "8 AM\u20137 PM"
                ],
                "Wednesday": [
                    "8 AM\u20137 PM"
                ],
                "Thursday": [
                    "8 AM\u20137 PM"
                ],
                "Friday": [
                    "8 AM\u20137 PM"
                ],
                "Saturday": [
                    "8 AM\u20137 PM"
                ]
            },
            "website": "https://meetgoodwill.org",
            "verified": true,
            "place_link": "https://www.google.com/maps/place/data=!3m1!4b1!4m2!3m1!1s0x5495b049bfccfb07:0xa736faba05d98cff",
            "cid": "12049093529945345279",
            "reviews_link": "https://search.google.com/local/reviews?placeid=ChIJB_vMv0mwlVQR_4zZBbr6Nqc&q=bin+stores+in+washington&authuser=0&hl=en&gl=US",
            "owner_id": "106951600469459247559",
            "owner_link": "https://maps.google.com/maps/contrib/106951600469459247559",
            "owner_name": "Goodwill Industries of the Columbia Willamette",
            "booking_link": null,
            "reservations_link": null,
            "business_status": "OPEN",
            "type": "Thrift store",
            "subtypes": [
                "Thrift store",
                "Donations center",
                "Non-profit organization",
                "Outlet store",
                "Recycling center"
            ],
            "photos_sample": [
                {
                    "photo_id": "AF1QipN_EnDOwQABu-0XHT0T7JLkkdPE2KH_4UkompFF",
                    "photo_url": "https://lh5.googleusercontent.com/p/AF1QipN_EnDOwQABu-0XHT0T7JLkkdPE2KH_4UkompFF",
                    "photo_url_large": "https://lh5.googleusercontent.com/p/AF1QipN_EnDOwQABu-0XHT0T7JLkkdPE2KH_4UkompFF=w4032-h3024-k-no",
                    "video_thumbnail_url": null,
                    "latitude": 45.68778219465618,
                    "longitude": -122.55077333810004,
                    "type": "photo",
                    "photo_datetime_utc": "2022-06-12T00:00:00.000Z",
                    "photo_timestamp": 1654992000
                }
            ],
            "reviews_per_rating": null,
            "photo_count": 68,
            "about": {
                "summary": "Long-standing nonprofit chain with a range of pre-owned clothing, housewares & more.",
                "details": {
                    "Service options": {
                        "In-store shopping": true,
                        "Onsite services": true,
                        "Delivery": false,
                        "Same-day delivery": false
                    },
                    "Accessibility": {
                        "Wheelchair accessible entrance": true,
                        "Wheelchair accessible parking lot": true
                    },
                    "Planning": {
                        "Quick visit": true
                    },
                    "Recycling": {
                        "Clothing": true,
                        "Electronics": true
                    },
                    "Payments": {
                        "Credit cards": true
                    }
                }
            },
            "address": "9025 NE 117th Ave, Vancouver, WA 98662",
            "order_link": null,
            "price_level": "$",
            "district": "Orchards",
            "street_address": "9025 NE 117th Ave",
            "city": "Vancouver",
            "zipcode": "98662",
            "state": "Washington",
            "country": "US",
            "emails_and_contacts": {
                "emails": [],
                "phone_numbers": [],
                "facebook": "https://www.facebook.com/meetgoodwill",
                "instagram": null,
                "yelp": "https://www.yelp.com/biz/goodwill-industries-of-the-columbia-willamette-happy-valley",
                "tiktok": null,
                "snapchat": null,
                "twitter": "https://twitter.com/meetgoodwill",
                "linkedin": "https://www.linkedin.com/company/goodwill-industries-of-the-columbia-willamette",
                "github": null,
                "youtube": null,
                "pinterest": "https://www.pinterest.com/meetgoodwill"
            },
            "no": 98
        }
    ]
}