{
    "status": "OK",
    "request_id": "ee7b0f1c-cd78-416f-a015-8ec7c48b9242",
    "parameters": {
        "query": "bin stores in north_carolina",
        "language": "en",
        "region": "us",
        "lat": 37.09024,
        "lng": -95.712891,
        "zoom": 13,
        "limit": 20,
        "offset": 0,
        "extract_emails_and_contacts": true
    },
    "data": [
        {
            "business_id": "0x8853afd2b1eb8e71:0xd82a79266aae86a1",
            "google_id": "0x8853afd2b1eb8e71:0xd82a79266aae86a1",
            "place_id": "ChIJcY7rsdKvU4gRoYauaiZ5Ktg",
            "google_mid": "/g/11w993ygxf",
            "phone_number": "+18312120897",
            "name": "North Carolina Bin Store",
            "latitude": 36.070618599999996,
            "longitude": -80.25485859999999,
            "full_address": "North Carolina Bin Store, 2101 Peters Creek Pkwy, Winston-Salem, NC 27127",
            "review_count": 45,
            "rating": 4.9,
            "timezone": "America/New_York",
            "opening_status": "Open \u22c5 Closes 6\u202fPM",
            "working_hours": {
                "Sunday": [
                    "10 AM\u20136 PM"
                ],
                "Monday": [
                    "10 AM\u20136 PM"
                ],
                "Tuesday": [
                    "10 AM\u20136 PM"
                ],
                "Wednesday": [
                    "10 AM\u20136 PM"
                ],
                "Thursday": [
                    "Closed"
                ],
                "Friday": [
                    "10 AM\u20136 PM"
                ],
                "Saturday": [
                    "10 AM\u20136 PM"
                ]
            },
            "website": null,
            "verified": true,
            "place_link": "https://www.google.com/maps/place/data=!3m1!4b1!4m2!3m1!1s0x8853afd2b1eb8e71:0xd82a79266aae86a1",
            "cid": "15576395467119822497",
            "reviews_link": "https://search.google.com/local/reviews?placeid=ChIJcY7rsdKvU4gRoYauaiZ5Ktg&q=bin+stores+in+north_carolina&authuser=0&hl=en&gl=US",
            "owner_id": "101662346434242791885",
            "owner_link": "https://maps.google.com/maps/contrib/101662346434242791885",
            "owner_name": "North Carolina Bin Store",
            "booking_link": null,
            "reservations_link": null,
            "business_status": "OPEN",
            "type": "Store",
            "subtypes": [
                "Store"
            ],
            "photos_sample": [
                {
                    "photo_id": "AF1QipNCwvCEd0xWTLXE3AHHV5evbz4zhUrUBio_kEt7",
                    "photo_url": "https://lh5.googleusercontent.com/p/AF1QipNCwvCEd0xWTLXE3AHHV5evbz4zhUrUBio_kEt7",
                    "photo_url_large": "https://lh5.googleusercontent.com/p/AF1QipNCwvCEd0xWTLXE3AHHV5evbz4zhUrUBio_kEt7=w3024-h4032-k-no",
                    "video_thumbnail_url": null,
                    "latitude": 36.070229499999996,
                    "longitude": -80.25484329999999,
                    "type": "photo",
                    "photo_datetime_utc": "2024-04-23T00:00:00.000Z",
                    "photo_timestamp": 1713830400
                }
            ],
            "reviews_per_rating": null,
            "photo_count": 4,
            "about": null,
            "address": "2101 Peters Creek Pkwy, Winston-Salem, NC 27127",
            "order_link": null,
            "price_level": null,
            "district": null,
            "street_address": "2101 Peters Creek Pkwy",
            "city": "Winston-Salem",
            "zipcode": "27127",
            "state": "North Carolina",
            "country": "US",
            "emails_and_contacts": {
                "emails": [],
                "phone_numbers": [],
                "facebook": null,
                "instagram": null,
                "yelp": null,
                "tiktok": null,
                "snapchat": null,
                "twitter": null,
                "linkedin": null,
                "github": null,
                "youtube": null,
                "pinterest": null
            },
            "no": 84
        },
        {
            "business_id": "0x8856bfab71e79f83:0xe153deaeff72a983",
            "google_id": "0x8856bfab71e79f83:0xe153deaeff72a983",
            "place_id": "ChIJg5_ncau_VogRg6ly_67eU-E",
            "google_mid": "/g/11rxw43m27",
            "phone_number": "+14708904368",
            "name": "Bin 5 Gastonia",
            "latitude": 35.244021,
            "longitude": -81.1340463,
            "full_address": "Bin 5 Gastonia, 1876 S New Hope Rd, Gastonia, NC 28054",
            "review_count": 338,
            "rating": 4.4,
            "timezone": "America/New_York",
            "opening_status": "Open \u22c5 Closes 5:45\u202fPM",
            "working_hours": {
                "Sunday": [
                    "9 AM\u20135:45 PM"
                ],
                "Monday": [
                    "9 AM\u20135:45 PM"
                ],
                "Tuesday": [
                    "9 AM\u20135:45 PM"
                ],
                "Wednesday": [
                    "9 AM\u201312 PM"
                ],
                "Thursday": [
                    "Closed"
                ],
                "Friday": [
                    "Closed"
                ],
                "Saturday": [
                    "9 AM\u20135:45 PM"
                ]
            },
            "website": "http://www.bin-five.com",
            "verified": true,
            "place_link": "https://www.google.com/maps/place/data=!3m1!4b1!4m2!3m1!1s0x8856bfab71e79f83:0xe153deaeff72a983",
            "cid": "16236565924792150403",
            "reviews_link": "https://search.google.com/local/reviews?placeid=ChIJg5_ncau_VogRg6ly_67eU-E&q=bin+stores+in+north_carolina&authuser=0&hl=en&gl=US",
            "owner_id": "115091529860169769709",
            "owner_link": "https://maps.google.com/maps/contrib/115091529860169769709",
            "owner_name": "Bin 5 Gastonia",
            "booking_link": null,
            "reservations_link": null,
            "business_status": "OPEN",
            "type": "Discount store",
            "subtypes": [
                "Discount store"
            ],
            "photos_sample": [
                {
                    "photo_id": "AF1QipPK8d5p57gGJ_ErcV9B08Y61bE4te3aTaYTBKZl",
                    "photo_url": "https://lh5.googleusercontent.com/p/AF1QipPK8d5p57gGJ_ErcV9B08Y61bE4te3aTaYTBKZl",
                    "photo_url_large": "https://lh5.googleusercontent.com/p/AF1QipPK8d5p57gGJ_ErcV9B08Y61bE4te3aTaYTBKZl=w4032-h3024-k-no",
                    "video_thumbnail_url": null,
                    "latitude": 35.24402101149529,
                    "longitude": -81.13404632595079,
                    "type": "photo",
                    "photo_datetime_utc": "2021-12-27T00:00:00.000Z",
                    "photo_timestamp": 1640563200
                }
            ],
            "reviews_per_rating": null,
            "photo_count": 4,
            "about": {
                "summary": null,
                "details": {
                    "Service options": {
                        "In-store shopping": true,
                        "Onsite services": true,
                        "Delivery": false,
                        "Same-day delivery": false
                    },
                    "Accessibility": {
                        "Wheelchair accessible entrance": true,
                        "Wheelchair accessible parking lot": true
                    },
                    "Amenities": {
                        "Wi-Fi": true
                    },
                    "Crowd": {
                        "LGBTQ+ friendly": true
                    },
                    "Planning": {
                        "Quick visit": true
                    },
                    "Payments": {
                        "Credit cards": true,
                        "Debit cards": true,
                        "NFC mobile payments": true
                    }
                }
            },
            "address": "1876 S New Hope Rd, Gastonia, NC 28054",
            "order_link": null,
            "price_level": null,
            "district": null,
            "street_address": "1876 S New Hope Rd",
            "city": "Gastonia",
            "zipcode": "28054",
            "state": "North Carolina",
            "country": "US",
            "emails_and_contacts": {
                "emails": [
                    "info@bin-five.com"
                ],
                "phone_numbers": [
                    "17739235133"
                ],
                "facebook": "https://www.facebook.com/bin5ive",
                "instagram": "https://www.instagram.com/bin5stores",
                "yelp": "https://www.yelp.com/biz/bin-five-hickory",
                "tiktok": null,
                "snapchat": null,
                "twitter": "https://twitter.com/fivebuckbin",
                "linkedin": null,
                "github": null,
                "youtube": null,
                "pinterest": null
            },
            "no": 84
        },
        {
            "business_id": "0x88531b545788eb33:0xe1e80f88f881f240",
            "google_id": "0x88531b545788eb33:0xe1e80f88f881f240",
            "place_id": "ChIJM-uIV1QbU4gRQPKB-IgP6OE",
            "google_mid": "/g/11kjdt6nzn",
            "phone_number": "+13367630032",
            "name": "Treasure Hunt Liquidators Bin Store",
            "latitude": 36.051429999999996,
            "longitude": -79.90429999999999,
            "full_address": "Treasure Hunt Liquidators Bin Store, 1312 Bridford Pkwy #101, Greensboro, NC 27407",
            "review_count": 176,
            "rating": 3.8,
            "timezone": "America/New_York",
            "opening_status": "Open \u22c5 Closes 7\u202fPM",
            "working_hours": {
                "Sunday": [
                    "10 AM\u20137 PM"
                ],
                "Monday": [
                    "10 AM\u20137 PM"
                ],
                "Tuesday": [
                    "10 AM\u20137 PM"
                ],
                "Wednesday": [
                    "10 AM\u20137 PM"
                ],
                "Thursday": [
                    "Closed"
                ],
                "Friday": [
                    "10 AM\u20137 PM"
                ],
                "Saturday": [
                    "10 AM\u20137 PM"
                ]
            },
            "website": "https://treasurehuntliquidators.com",
            "verified": true,
            "place_link": "https://www.google.com/maps/place/data=!3m1!4b1!4m2!3m1!1s0x88531b545788eb33:0xe1e80f88f881f240",
            "cid": "16278277934089892416",
            "reviews_link": "https://search.google.com/local/reviews?placeid=ChIJM-uIV1QbU4gRQPKB-IgP6OE&q=bin+stores+in+north_carolina&authuser=0&hl=en&gl=US",
            "owner_id": "116318386740703893355",
            "owner_link": "https://maps.google.com/maps/contrib/116318386740703893355",
            "owner_name": "Treasure Hunt Liquidators Bin Store",
            "booking_link": null,
            "reservations_link": null,
            "business_status": "OPEN",
            "type": "Discount store",
            "subtypes": [
                "Discount store"
            ],
            "photos_sample": [
                {
                    "photo_id": "AF1QipPrRw6zkRFZ4Vj2ipqv9K-L881iULsqUBQKeMHt",
                    "photo_url": "https://lh5.googleusercontent.com/p/AF1QipPrRw6zkRFZ4Vj2ipqv9K-L881iULsqUBQKeMHt",
                    "photo_url_large": "https://lh5.googleusercontent.com/p/AF1QipPrRw6zkRFZ4Vj2ipqv9K-L881iULsqUBQKeMHt=w4032-h2268-k-no",
                    "video_thumbnail_url": null,
                    "latitude": 36.05142997624378,
                    "longitude": -79.90429997604073,
                    "type": "photo",
                    "photo_datetime_utc": "2023-07-16T00:00:00.000Z",
                    "photo_timestamp": 1689465600
                }
            ],
            "reviews_per_rating": null,
            "photo_count": 4,
            "about": {
                "summary": null,
                "details": {
                    "Service options": {
                        "Delivery": false,
                        "Same-day delivery": false
                    },
                    "Accessibility": {
                        "Wheelchair accessible entrance": true,
                        "Wheelchair accessible parking lot": true
                    },
                    "Payments": {
                        "Credit cards": true,
                        "Debit cards": true
                    }
                }
            },
            "address": "1312 Bridford Pkwy #101, Greensboro, NC 27407",
            "order_link": null,
            "price_level": null,
            "district": "Idle Acres",
            "street_address": "1312 Bridford Pkwy #101",
            "city": "Greensboro",
            "zipcode": "27407",
            "state": "North Carolina",
            "country": "US",
            "emails_and_contacts": {
                "emails": [],
                "phone_numbers": [],
                "facebook": "https://www.facebook.com/TreasureHuntLiquidators",
                "instagram": null,
                "yelp": "https://www.yelp.com/biz/treasure-hunt-liquidators-norfolk",
                "tiktok": "https://www.tiktok.com/@treasurehuntliquidators",
                "snapchat": null,
                "twitter": null,
                "linkedin": "https://www.linkedin.com/company/treasure-hunt-liquidators",
                "github": null,
                "youtube": null,
                "pinterest": null
            },
            "no": 84
        },
        {
            "business_id": "0x89ac27f80a91fd51:0x6a8fc45f85cea0bc",
            "google_id": "0x89ac27f80a91fd51:0x6a8fc45f85cea0bc",
            "place_id": "ChIJUf2RCvgnrIkRvKDOhV_Ej2o",
            "google_mid": "/g/11jt7rkxhc",
            "phone_number": "+12522968150",
            "name": "DaaBIN Store - Wilson, NC",
            "latitude": 35.7603912,
            "longitude": -77.9861907,
            "full_address": "DaaBIN Store - Wilson, NC, 4353 Raleigh Rd Pkwy W, Wilson, NC 27896",
            "review_count": 166,
            "rating": 4.8,
            "timezone": "America/New_York",
            "opening_status": "Open \u22c5 Closes 5\u202fPM",
            "working_hours": {
                "Sunday": [
                    "10 AM\u20135 PM"
                ],
                "Monday": [
                    "9 AM\u20137 PM"
                ],
                "Tuesday": [
                    "9 AM\u20137 PM"
                ],
                "Wednesday": [
                    "9 AM\u201312 PM"
                ],
                "Thursday": [
                    "Closed"
                ],
                "Friday": [
                    "Closed"
                ],
                "Saturday": [
                    "9 AM\u20137 PM"
                ]
            },
            "website": "https://daabinstore.com/wilson-nc",
            "verified": true,
            "place_link": "https://www.google.com/maps/place/data=!3m1!4b1!4m2!3m1!1s0x89ac27f80a91fd51:0x6a8fc45f85cea0bc",
            "cid": "7678571804235833532",
            "reviews_link": "https://search.google.com/local/reviews?placeid=ChIJUf2RCvgnrIkRvKDOhV_Ej2o&q=bin+stores+in+north_carolina&authuser=0&hl=en&gl=US",
            "owner_id": "111686343230865727270",
            "owner_link": "https://maps.google.com/maps/contrib/111686343230865727270",
            "owner_name": "DaaBIN Store - Wilson, NC",
            "booking_link": null,
            "reservations_link": null,
            "business_status": "OPEN",
            "type": "Discount store",
            "subtypes": [
                "Discount store"
            ],
            "photos_sample": [
                {
                    "photo_id": "AF1QipM4NSd7_wjrlbGbZbUnPfGHO2Z1Oy99gF-BLyUm",
                    "photo_url": "https://lh5.googleusercontent.com/p/AF1QipM4NSd7_wjrlbGbZbUnPfGHO2Z1Oy99gF-BLyUm",
                    "photo_url_large": "https://lh5.googleusercontent.com/p/AF1QipM4NSd7_wjrlbGbZbUnPfGHO2Z1Oy99gF-BLyUm=w4032-h3024-k-no",
                    "video_thumbnail_url": null,
                    "latitude": 35.7606745,
                    "longitude": -77.9860362,
                    "type": "photo",
                    "photo_datetime_utc": "2023-05-28T00:00:00.000Z",
                    "photo_timestamp": 1685232000
                }
            ],
            "reviews_per_rating": null,
            "photo_count": 4,
            "about": {
                "summary": null,
                "details": {
                    "Service options": {
                        "Delivery": false,
                        "Same-day delivery": false
                    },
                    "Accessibility": {
                        "Wheelchair accessible entrance": true,
                        "Wheelchair accessible parking lot": true
                    },
                    "Planning": {
                        "Quick visit": true
                    },
                    "Payments": {
                        "Credit cards": true,
                        "Debit cards": true
                    }
                }
            },
            "address": "4353 Raleigh Rd Pkwy W, Wilson, NC 27896",
            "order_link": null,
            "price_level": null,
            "district": null,
            "street_address": "4353 Raleigh Rd Pkwy W",
            "city": "Wilson",
            "zipcode": "27896",
            "state": "North Carolina",
            "country": "US",
            "emails_and_contacts": {
                "emails": [],
                "phone_numbers": [],
                "facebook": null,
                "instagram": null,
                "yelp": null,
                "tiktok": null,
                "snapchat": null,
                "twitter": null,
                "linkedin": null,
                "github": null,
                "youtube": null,
                "pinterest": null
            },
            "no": 84
        },
        {
            "business_id": "0x885319d17af190d9:0xee3a7992e1169f5a",
            "google_id": "0x885319d17af190d9:0xee3a7992e1169f5a",
            "place_id": "ChIJ2ZDxetEZU4gRWp8W4ZJ5Ou4",
            "google_mid": "/g/11ppdlq6m3",
            "phone_number": "+13369915081",
            "name": "Paradise Bins",
            "latitude": 35.899536999999995,
            "longitude": -79.947968,
            "full_address": "Paradise Bins, 10106-B S Main St, Archdale, NC 27263",
            "review_count": 109,
            "rating": 4.3,
            "timezone": "America/New_York",
            "opening_status": "Closes soon \u22c5 4\u202fPM \u22c5 Opens 9\u202fAM Mon",
            "working_hours": {
                "Sunday": [
                    "10 AM\u20134 PM"
                ],
                "Monday": [
                    "9 AM\u20136 PM"
                ],
                "Tuesday": [
                    "9 AM\u20136 PM"
                ],
                "Wednesday": [
                    "9 AM\u20136 PM"
                ],
                "Thursday": [
                    "9 AM\u20136 PM"
                ],
                "Friday": [
                    "Closed"
                ],
                "Saturday": [
                    "9 AM\u20136 PM"
                ]
            },
            "website": "https://www.facebook.com/profile.php?id=100063945558916",
            "verified": true,
            "place_link": "https://www.google.com/maps/place/data=!3m1!4b1!4m2!3m1!1s0x885319d17af190d9:0xee3a7992e1169f5a",
            "cid": "17166166601424609114",
            "reviews_link": "https://search.google.com/local/reviews?placeid=ChIJ2ZDxetEZU4gRWp8W4ZJ5Ou4&q=bin+stores+in+north_carolina&authuser=0&hl=en&gl=US",
            "owner_id": "101708908680822770367",
            "owner_link": "https://maps.google.com/maps/contrib/101708908680822770367",
            "owner_name": "Paradise Bins",
            "booking_link": null,
            "reservations_link": null,
            "business_status": "OPEN",
            "type": "Discount store",
            "subtypes": [
                "Discount store"
            ],
            "photos_sample": [
                {
                    "photo_id": "AF1QipMAyTOwLvNTlEs1qbjOJdzUrMxQRYSzUmGHsM5B",
                    "photo_url": "https://lh5.googleusercontent.com/p/AF1QipMAyTOwLvNTlEs1qbjOJdzUrMxQRYSzUmGHsM5B",
                    "photo_url_large": "https://lh5.googleusercontent.com/p/AF1QipMAyTOwLvNTlEs1qbjOJdzUrMxQRYSzUmGHsM5B=w3024-h4032-k-no",
                    "video_thumbnail_url": null,
                    "latitude": 35.899741899999995,
                    "longitude": -79.94783319999999,
                    "type": "photo",
                    "photo_datetime_utc": "2022-12-17T00:00:00.000Z",
                    "photo_timestamp": 1671235200
                }
            ],
            "reviews_per_rating": null,
            "photo_count": 4,
            "about": {
                "summary": null,
                "details": {
                    "From the business": {
                        "Small business": true
                    },
                    "Service options": {
                        "In-store shopping": true,
                        "Delivery": false,
                        "Same-day delivery": false
                    },
                    "Accessibility": {
                        "Wheelchair accessible entrance": true,
                        "Wheelchair accessible parking lot": true,
                        "Wheelchair accessible restroom": true
                    },
                    "Planning": {
                        "Quick visit": true
                    },
                    "Payments": {
                        "Credit cards": true,
                        "Debit cards": true,
                        "NFC mobile payments": true
                    }
                }
            },
            "address": "10106-B S Main St, Archdale, NC 27263",
            "order_link": null,
            "price_level": null,
            "district": null,
            "street_address": "10106-B S Main St",
            "city": "Archdale",
            "zipcode": "27263",
            "state": "North Carolina",
            "country": "US",
            "emails_and_contacts": {
                "emails": [],
                "phone_numbers": [],
                "facebook": null,
                "instagram": null,
                "yelp": null,
                "tiktok": null,
                "snapchat": null,
                "twitter": null,
                "linkedin": null,
                "github": null,
                "youtube": null,
                "pinterest": null
            },
            "no": 84
        },
        {
            "business_id": "0x89a9f550aad96c19:0x9301b43ccf06452f",
            "google_id": "0x89a9f550aad96c19:0x9301b43ccf06452f",
            "place_id": "ChIJGWzZqlD1qYkRL0UGzzy0AZM",
            "google_mid": "/g/11t6z1rfph",
            "phone_number": "+19108994066",
            "name": "Crazy Deals Outlet Bin Store",
            "latitude": 34.2412871,
            "longitude": -77.89082069999999,
            "full_address": "Crazy Deals Outlet Bin Store, 4348 Market St, Wilmington, NC 28403",
            "review_count": 56,
            "rating": 4.4,
            "timezone": "America/New_York",
            "opening_status": "Open \u22c5 Closes 6\u202fPM",
            "working_hours": {
                "Sunday": [
                    "11 AM\u20136 PM"
                ],
                "Monday": [
                    "10 AM\u20137 PM"
                ],
                "Tuesday": [
                    "10 AM\u20137 PM"
                ],
                "Wednesday": [
                    "10 AM\u20137 PM"
                ],
                "Thursday": [
                    "Closed"
                ],
                "Friday": [
                    "10 AM\u20137 PM"
                ],
                "Saturday": [
                    "10 AM\u20137 PM"
                ]
            },
            "website": null,
            "verified": true,
            "place_link": "https://www.google.com/maps/place/data=!3m1!4b1!4m2!3m1!1s0x89a9f550aad96c19:0x9301b43ccf06452f",
            "cid": "10592945971816449327",
            "reviews_link": "https://search.google.com/local/reviews?placeid=ChIJGWzZqlD1qYkRL0UGzzy0AZM&q=bin+stores+in+north_carolina&authuser=0&hl=en&gl=US",
            "owner_id": "102900654532180071476",
            "owner_link": "https://maps.google.com/maps/contrib/102900654532180071476",
            "owner_name": "Crazy Deals Outlet Bin Store",
            "booking_link": null,
            "reservations_link": null,
            "business_status": "OPEN",
            "type": "Discount store",
            "subtypes": [
                "Discount store"
            ],
            "photos_sample": [
                {
                    "photo_id": "AF1QipOC700h9eSXqQCOFfak6u3MU5bblIyMI_kh8N8Y",
                    "photo_url": "https://lh5.googleusercontent.com/p/AF1QipOC700h9eSXqQCOFfak6u3MU5bblIyMI_kh8N8Y",
                    "photo_url_large": "https://lh5.googleusercontent.com/p/AF1QipOC700h9eSXqQCOFfak6u3MU5bblIyMI_kh8N8Y=w4032-h3024-k-no",
                    "video_thumbnail_url": null,
                    "latitude": 34.241318899999996,
                    "longitude": -77.8906591,
                    "type": "photo",
                    "photo_datetime_utc": "2023-03-02T00:00:00.000Z",
                    "photo_timestamp": 1677715200
                }
            ],
            "reviews_per_rating": null,
            "photo_count": 182,
            "about": {
                "summary": null,
                "details": {
                    "From the business": {
                        "Small business": true
                    },
                    "Service options": {
                        "Delivery": false,
                        "Same-day delivery": false
                    },
                    "Accessibility": {
                        "Wheelchair accessible entrance": true,
                        "Wheelchair accessible parking lot": true
                    },
                    "Payments": {
                        "Credit cards": true,
                        "Debit cards": true,
                        "NFC mobile payments": true
                    }
                }
            },
            "address": "4348 Market St, Wilmington, NC 28403",
            "order_link": null,
            "price_level": null,
            "district": null,
            "street_address": "4348 Market St",
            "city": "Wilmington",
            "zipcode": "28403",
            "state": "North Carolina",
            "country": "US",
            "emails_and_contacts": {
                "emails": [],
                "phone_numbers": [],
                "facebook": null,
                "instagram": null,
                "yelp": null,
                "tiktok": null,
                "snapchat": null,
                "twitter": null,
                "linkedin": null,
                "github": null,
                "youtube": null,
                "pinterest": null
            },
            "no": 84
        },
        {
            "business_id": "0x8853995e33621683:0x7aa4047c21439e30",
            "google_id": "0x8853995e33621683:0x7aa4047c21439e30",
            "place_id": "ChIJgxZiM16ZU4gRMJ5DIXwEpHo",
            "google_mid": "/g/11q8rszlx5",
            "phone_number": null,
            "name": "Bargains by the Bin",
            "latitude": 35.819636599999995,
            "longitude": -80.2381163,
            "full_address": "Bargains by the Bin, 294 N Talbert Blvd, Lexington, NC 27292",
            "review_count": 62,
            "rating": 4.6,
            "timezone": "America/New_York",
            "opening_status": "Closes soon \u22c5 4\u202fPM \u22c5 Opens 10\u202fAM Mon",
            "working_hours": {
                "Sunday": [
                    "10 AM\u20134 PM"
                ],
                "Monday": [
                    "10 AM\u20136 PM"
                ],
                "Tuesday": [
                    "10 AM\u20132 PM"
                ],
                "Wednesday": [
                    "Closed"
                ],
                "Thursday": [
                    "Closed"
                ],
                "Friday": [
                    "Closed"
                ],
                "Saturday": [
                    "10 AM\u20136 PM"
                ]
            },
            "website": null,
            "verified": true,
            "place_link": "https://www.google.com/maps/place/data=!3m1!4b1!4m2!3m1!1s0x8853995e33621683:0x7aa4047c21439e30",
            "cid": "8837193299988291120",
            "reviews_link": "https://search.google.com/local/reviews?placeid=ChIJgxZiM16ZU4gRMJ5DIXwEpHo&q=bin+stores+in+north_carolina&authuser=0&hl=en&gl=US",
            "owner_id": "110964615085891965273",
            "owner_link": "https://maps.google.com/maps/contrib/110964615085891965273",
            "owner_name": "Bargains by the Bin",
            "booking_link": null,
            "reservations_link": null,
            "business_status": "OPEN",
            "type": "Store",
            "subtypes": [
                "Store"
            ],
            "photos_sample": [
                {
                    "photo_id": "AF1QipOA7Aod-zsSdT-GWh85JyN0W3vYRqvHRwfztSpT",
                    "photo_url": "https://lh5.googleusercontent.com/p/AF1QipOA7Aod-zsSdT-GWh85JyN0W3vYRqvHRwfztSpT",
                    "photo_url_large": "https://lh5.googleusercontent.com/p/AF1QipOA7Aod-zsSdT-GWh85JyN0W3vYRqvHRwfztSpT=w4032-h3024-k-no",
                    "video_thumbnail_url": null,
                    "latitude": 35.8197124,
                    "longitude": -80.2381834,
                    "type": "photo",
                    "photo_datetime_utc": "2021-10-03T00:00:00.000Z",
                    "photo_timestamp": 1633219200
                }
            ],
            "reviews_per_rating": null,
            "photo_count": 221,
            "about": {
                "summary": null,
                "details": {
                    "From the business": {
                        "Small business": true
                    },
                    "Service options": {
                        "Delivery": false,
                        "Same-day delivery": false
                    },
                    "Accessibility": {
                        "Wheelchair accessible entrance": true,
                        "Wheelchair accessible parking lot": true
                    },
                    "Crowd": {
                        "LGBTQ+ friendly": true,
                        "Transgender safespace": true
                    },
                    "Payments": {
                        "Cash-only": true,
                        "Credit cards": true,
                        "Debit cards": true,
                        "NFC mobile payments": true
                    }
                }
            },
            "address": "294 N Talbert Blvd, Lexington, NC 27292",
            "order_link": null,
            "price_level": null,
            "district": null,
            "street_address": "294 N Talbert Blvd",
            "city": "Lexington",
            "zipcode": "27292",
            "state": "North Carolina",
            "country": "US",
            "emails_and_contacts": {
                "emails": [],
                "phone_numbers": [],
                "facebook": null,
                "instagram": null,
                "yelp": null,
                "tiktok": null,
                "snapchat": null,
                "twitter": null,
                "linkedin": null,
                "github": null,
                "youtube": null,
                "pinterest": null
            },
            "no": 84
        },
        {
            "business_id": "0x88547ddb9df22627:0xa84e9b44e2c786a6",
            "google_id": "0x88547ddb9df22627:0xa84e9b44e2c786a6",
            "place_id": "ChIJJybyndt9VIgRpobH4kSbTqg",
            "google_mid": "/g/11s0kc502y",
            "phone_number": "+17045505989",
            "name": "Ebenezer's Bins and Bargains",
            "latitude": 35.3627019,
            "longitude": -80.154088,
            "full_address": "Ebenezer's Bins and Bargains, 2452 Badin Rd, Albemarle, NC 28001",
            "review_count": 89,
            "rating": 4.7,
            "timezone": "America/New_York",
            "opening_status": "Closed \u22c5 Opens 10\u202fAM Mon",
            "working_hours": {
                "Sunday": [
                    "Closed"
                ],
                "Monday": [
                    "10 AM\u20135 PM"
                ],
                "Tuesday": [
                    "10 AM\u20135 PM"
                ],
                "Wednesday": [
                    "10 AM\u20135 PM"
                ],
                "Thursday": [
                    "10 AM\u20135 PM"
                ],
                "Friday": [
                    "10 AM\u20135 PM"
                ],
                "Saturday": [
                    "10 AM\u20135 PM"
                ]
            },
            "website": null,
            "verified": true,
            "place_link": "https://www.google.com/maps/place/data=!3m1!4b1!4m2!3m1!1s0x88547ddb9df22627:0xa84e9b44e2c786a6",
            "cid": "12127801566720132774",
            "reviews_link": "https://search.google.com/local/reviews?placeid=ChIJJybyndt9VIgRpobH4kSbTqg&q=bin+stores+in+north_carolina&authuser=0&hl=en&gl=US",
            "owner_id": "103434302822253716445",
            "owner_link": "https://maps.google.com/maps/contrib/103434302822253716445",
            "owner_name": "Ebenezer's Bins and Bargains",
            "booking_link": null,
            "reservations_link": null,
            "business_status": "OPEN",
            "type": "Store",
            "subtypes": [
                "Store"
            ],
            "photos_sample": [
                {
                    "photo_id": "AF1QipPm7GAQWF00VjiSgYJ80tMKxOVQ0kjCDFe6oez-",
                    "photo_url": "https://lh5.googleusercontent.com/p/AF1QipPm7GAQWF00VjiSgYJ80tMKxOVQ0kjCDFe6oez-",
                    "photo_url_large": "https://lh5.googleusercontent.com/p/AF1QipPm7GAQWF00VjiSgYJ80tMKxOVQ0kjCDFe6oez-=w4032-h3024-k-no",
                    "video_thumbnail_url": null,
                    "latitude": 35.3629633,
                    "longitude": -80.1541026,
                    "type": "photo",
                    "photo_datetime_utc": "2022-02-15T00:00:00.000Z",
                    "photo_timestamp": 1644883200
                }
            ],
            "reviews_per_rating": null,
            "photo_count": 4,
            "about": {
                "summary": null,
                "details": {
                    "From the business": {
                        "Small business": true
                    },
                    "Service options": {
                        "In-store shopping": true,
                        "Delivery": false,
                        "Same-day delivery": false
                    },
                    "Accessibility": {
                        "Wheelchair accessible entrance": true,
                        "Wheelchair accessible parking lot": true
                    },
                    "Payments": {
                        "Credit cards": true
                    }
                }
            },
            "address": "2452 Badin Rd, Albemarle, NC 28001",
            "order_link": null,
            "price_level": null,
            "district": null,
            "street_address": "2452 Badin Rd",
            "city": "Albemarle",
            "zipcode": "28001",
            "state": "North Carolina",
            "country": "US",
            "emails_and_contacts": {
                "emails": [],
                "phone_numbers": [],
                "facebook": null,
                "instagram": null,
                "yelp": null,
                "tiktok": null,
                "snapchat": null,
                "twitter": null,
                "linkedin": null,
                "github": null,
                "youtube": null,
                "pinterest": null
            },
            "no": 84
        },
        {
            "business_id": "0x88531b4a3895dbe5:0xbff8e7027f9cc4d5",
            "google_id": "0x88531b4a3895dbe5:0xbff8e7027f9cc4d5",
            "place_id": "ChIJ5duVOEobU4gR1cScfwLn-L8",
            "google_mid": "/g/11jyb19cs8",
            "phone_number": "+13366764433",
            "name": "Toteboys Bin Store",
            "latitude": 36.0366703,
            "longitude": -79.8595679,
            "full_address": "Toteboys Bin Store, 3901 W Gate City Blvd, Greensboro, NC 27407",
            "review_count": 61,
            "rating": 4.3,
            "timezone": "America/New_York",
            "opening_status": "Open \u22c5 Closes 6\u202fPM",
            "working_hours": {
                "Sunday": [
                    "10 AM\u20136 PM"
                ],
                "Monday": [
                    "10 AM\u20136 PM"
                ],
                "Tuesday": [
                    "Closed"
                ],
                "Wednesday": [
                    "10 AM\u20136 PM"
                ],
                "Thursday": [
                    "10 AM\u20136 PM"
                ],
                "Friday": [
                    "10 AM\u20136 PM"
                ],
                "Saturday": [
                    "10 AM\u20136 PM"
                ]
            },
            "website": "http://www.toteboys.com",
            "verified": true,
            "place_link": "https://www.google.com/maps/place/data=!3m1!4b1!4m2!3m1!1s0x88531b4a3895dbe5:0xbff8e7027f9cc4d5",
            "cid": "13833060253385409749",
            "reviews_link": "https://search.google.com/local/reviews?placeid=ChIJ5duVOEobU4gR1cScfwLn-L8&q=bin+stores+in+north_carolina&authuser=0&hl=en&gl=US",
            "owner_id": "115216410274504072897",
            "owner_link": "https://maps.google.com/maps/contrib/115216410274504072897",
            "owner_name": "Toteboys Bin Store",
            "booking_link": null,
            "reservations_link": null,
            "business_status": "OPEN",
            "type": "Discount store",
            "subtypes": [
                "Discount store",
                "Store"
            ],
            "photos_sample": [
                {
                    "photo_id": "AF1QipP51U_8-wBHSvhmTF8mjsUcMPUywj0zbjHvqiPi",
                    "photo_url": "https://lh5.googleusercontent.com/p/AF1QipP51U_8-wBHSvhmTF8mjsUcMPUywj0zbjHvqiPi",
                    "photo_url_large": "https://lh5.googleusercontent.com/p/AF1QipP51U_8-wBHSvhmTF8mjsUcMPUywj0zbjHvqiPi=w4032-h3024-k-no",
                    "video_thumbnail_url": null,
                    "latitude": 36.036924299999995,
                    "longitude": -79.8596363,
                    "type": "photo",
                    "photo_datetime_utc": "2022-11-18T00:00:00.000Z",
                    "photo_timestamp": 1668729600
                }
            ],
            "reviews_per_rating": null,
            "photo_count": 4,
            "about": {
                "summary": null,
                "details": {
                    "Service options": {
                        "Delivery": false,
                        "Same-day delivery": false
                    },
                    "Accessibility": {
                        "Wheelchair accessible entrance": true,
                        "Wheelchair accessible parking lot": true
                    },
                    "Payments": {
                        "Credit cards": true
                    }
                }
            },
            "address": "3901 W Gate City Blvd, Greensboro, NC 27407",
            "order_link": null,
            "price_level": null,
            "district": null,
            "street_address": "3901 W Gate City Blvd",
            "city": "Greensboro",
            "zipcode": "27407",
            "state": "North Carolina",
            "country": "US",
            "emails_and_contacts": {
                "emails": [],
                "phone_numbers": [
                    "9292426868"
                ],
                "facebook": "https://www.facebook.com/fbtoteboys",
                "instagram": "https://www.instagram.com/toteboys",
                "yelp": null,
                "tiktok": null,
                "snapchat": null,
                "twitter": null,
                "linkedin": null,
                "github": null,
                "youtube": null,
                "pinterest": null
            },
            "no": 84
        },
        {
            "business_id": "0x89a94beeb8d7c6ad:0x889488e33ae0177d",
            "google_id": "0x89a94beeb8d7c6ad:0x889488e33ae0177d",
            "place_id": "ChIJrcbXuO5LqYkRfRfgOuOIlIg",
            "google_mid": "/g/11shnyycp8",
            "phone_number": "+12526430559",
            "name": "DaaBIN Store - Kinston, NC",
            "latitude": 35.2525177,
            "longitude": -77.602272,
            "full_address": "DaaBIN Store - Kinston, NC, 1030 W New Bern Rd, Kinston, NC 28504",
            "review_count": 173,
            "rating": 4.7,
            "timezone": "America/New_York",
            "opening_status": "Open \u22c5 Closes 5\u202fPM",
            "working_hours": {
                "Sunday": [
                    "12\u20135 PM"
                ],
                "Monday": [
                    "9 AM\u20137 PM"
                ],
                "Tuesday": [
                    "9 AM\u20137 PM"
                ],
                "Wednesday": [
                    "9 AM\u201312 PM"
                ],
                "Thursday": [
                    "Closed"
                ],
                "Friday": [
                    "Closed"
                ],
                "Saturday": [
                    "9 AM\u20137 PM"
                ]
            },
            "website": "https://daabinstore.com/kinston",
            "verified": true,
            "place_link": "https://www.google.com/maps/place/data=!3m1!4b1!4m2!3m1!1s0x89a94beeb8d7c6ad:0x889488e33ae0177d",
            "cid": "9841641595238094717",
            "reviews_link": "https://search.google.com/local/reviews?placeid=ChIJrcbXuO5LqYkRfRfgOuOIlIg&q=bin+stores+in+north_carolina&authuser=0&hl=en&gl=US",
            "owner_id": "117433281365812882660",
            "owner_link": "https://maps.google.com/maps/contrib/117433281365812882660",
            "owner_name": "DaaBIN Store - Kinston, NC",
            "booking_link": null,
            "reservations_link": null,
            "business_status": "OPEN",
            "type": "Discount store",
            "subtypes": [
                "Discount store"
            ],
            "photos_sample": [
                {
                    "photo_id": "AF1QipPKZmTY76QXUOSdJscXON8tac-vS6WM3F2gTI9H",
                    "photo_url": "https://lh5.googleusercontent.com/p/AF1QipPKZmTY76QXUOSdJscXON8tac-vS6WM3F2gTI9H",
                    "photo_url_large": "https://lh5.googleusercontent.com/p/AF1QipPKZmTY76QXUOSdJscXON8tac-vS6WM3F2gTI9H=w4032-h1908-k-no",
                    "video_thumbnail_url": null,
                    "latitude": 35.2526288,
                    "longitude": -77.60213759999999,
                    "type": "photo",
                    "photo_datetime_utc": "2023-05-28T00:00:00.000Z",
                    "photo_timestamp": 1685232000
                }
            ],
            "reviews_per_rating": null,
            "photo_count": 4,
            "about": {
                "summary": null,
                "details": {
                    "Service options": {
                        "Delivery": false,
                        "Same-day delivery": false
                    },
                    "Accessibility": {
                        "Wheelchair accessible entrance": true,
                        "Wheelchair accessible parking lot": true
                    },
                    "Planning": {
                        "Quick visit": true
                    },
                    "Payments": {
                        "Credit cards": true,
                        "Debit cards": true
                    }
                }
            },
            "address": "1030 W New Bern Rd, Kinston, NC 28504",
            "order_link": null,
            "price_level": null,
            "district": null,
            "street_address": "1030 W New Bern Rd",
            "city": "Kinston",
            "zipcode": "28504",
            "state": "North Carolina",
            "country": "US",
            "emails_and_contacts": {
                "emails": [],
                "phone_numbers": [],
                "facebook": null,
                "instagram": null,
                "yelp": null,
                "tiktok": null,
                "snapchat": null,
                "twitter": null,
                "linkedin": null,
                "github": null,
                "youtube": null,
                "pinterest": null
            },
            "no": 84
        },
        {
            "business_id": "0x89ac216c384bbb17:0x7759618d0fccbda1",
            "google_id": "0x89ac216c384bbb17:0x7759618d0fccbda1",
            "place_id": "ChIJF7tLOGwhrIkRob3MD41hWXc",
            "google_mid": "/g/11kjyjj0by",
            "phone_number": "+12526402636",
            "name": "QuickBins Liquidators",
            "latitude": 35.7172889,
            "longitude": -77.9361572,
            "full_address": "QuickBins Liquidators, 925 Ward Blvd, Wilson, NC 27893",
            "review_count": 21,
            "rating": 4.2,
            "timezone": "America/New_York",
            "opening_status": "Open \u22c5 Closes 5\u202fPM",
            "working_hours": {
                "Sunday": [
                    "11 AM\u20135 PM"
                ],
                "Monday": [
                    "10 AM\u20137 PM"
                ],
                "Tuesday": [
                    "10 AM\u20137 PM"
                ],
                "Wednesday": [
                    "10 AM\u20137 PM"
                ],
                "Thursday": [
                    "Closed"
                ],
                "Friday": [
                    "10 AM\u20137 PM"
                ],
                "Saturday": [
                    "10 AM\u20136 PM"
                ]
            },
            "website": null,
            "verified": true,
            "place_link": "https://www.google.com/maps/place/data=!3m1!4b1!4m2!3m1!1s0x89ac216c384bbb17:0x7759618d0fccbda1",
            "cid": "8600012221924031905",
            "reviews_link": "https://search.google.com/local/reviews?placeid=ChIJF7tLOGwhrIkRob3MD41hWXc&q=bin+stores+in+north_carolina&authuser=0&hl=en&gl=US",
            "owner_id": "100901860264638138000",
            "owner_link": "https://maps.google.com/maps/contrib/100901860264638138000",
            "owner_name": "QuickBins Liquidators",
            "booking_link": null,
            "reservations_link": null,
            "business_status": "OPEN",
            "type": "Discount store",
            "subtypes": [
                "Discount store",
                "Clothing store",
                "Craft store",
                "Dollar store",
                "Gift shop",
                "Kitchen supply store",
                "Liquidator",
                "School supply store",
                "Toy store"
            ],
            "photos_sample": [
                {
                    "photo_id": "AF1QipNX0qvy3P6XEdpTDGAq-q89en5MkSDOzDyWfIsv",
                    "photo_url": "https://lh5.googleusercontent.com/p/AF1QipNX0qvy3P6XEdpTDGAq-q89en5MkSDOzDyWfIsv",
                    "photo_url_large": "https://lh5.googleusercontent.com/p/AF1QipNX0qvy3P6XEdpTDGAq-q89en5MkSDOzDyWfIsv=w1024-h768-k-no",
                    "video_thumbnail_url": null,
                    "latitude": 35.7173758,
                    "longitude": -77.9358512,
                    "type": "photo",
                    "photo_datetime_utc": "2023-05-27T00:00:00.000Z",
                    "photo_timestamp": 1685145600
                }
            ],
            "reviews_per_rating": null,
            "photo_count": 45,
            "about": {
                "summary": null,
                "details": {
                    "From the business": {
                        "Small business": true
                    },
                    "Service options": {
                        "In-store pickup": true,
                        "Delivery": false,
                        "Same-day delivery": false
                    },
                    "Accessibility": {
                        "Wheelchair accessible entrance": true,
                        "Wheelchair accessible parking lot": true
                    },
                    "Payments": {
                        "Credit cards": true,
                        "Debit cards": true
                    }
                }
            },
            "address": "925 Ward Blvd, Wilson, NC 27893",
            "order_link": null,
            "price_level": null,
            "district": null,
            "street_address": "925 Ward Blvd",
            "city": "Wilson",
            "zipcode": "27893",
            "state": "North Carolina",
            "country": "US",
            "emails_and_contacts": {
                "emails": [],
                "phone_numbers": [],
                "facebook": null,
                "instagram": null,
                "yelp": null,
                "tiktok": null,
                "snapchat": null,
                "twitter": null,
                "linkedin": null,
                "github": null,
                "youtube": null,
                "pinterest": null
            },
            "no": 84
        },
        {
            "business_id": "0x88540f0a39ec8997:0x1a37416f8c999eac",
            "google_id": "0x88540f0a39ec8997:0x1a37416f8c999eac",
            "place_id": "ChIJl4nsOQoPVIgRrJ6ZjG9BNxo",
            "google_mid": "/g/11tdl1skdv",
            "phone_number": null,
            "name": "Where Ya Bin Concord",
            "latitude": 35.419796999999996,
            "longitude": -80.5716633,
            "full_address": "Where Ya Bin Concord, 30 Branchview Dr NE, Concord, NC 28025",
            "review_count": 356,
            "rating": 3.3,
            "timezone": "America/New_York",
            "opening_status": "Open \u22c5 Closes 7\u202fPM",
            "working_hours": {
                "Sunday": [
                    "9 AM\u20137 PM"
                ],
                "Monday": [
                    "9 AM\u20138 PM"
                ],
                "Tuesday": [
                    "9 AM\u20138 PM"
                ],
                "Wednesday": [
                    "9 AM\u20138 PM"
                ],
                "Thursday": [
                    "9 AM\u20134 PM"
                ],
                "Friday": [
                    "8 AM\u20138 PM"
                ],
                "Saturday": [
                    "9 AM\u20138 PM"
                ]
            },
            "website": "https://www.whereyabinstores.com",
            "verified": true,
            "place_link": "https://www.google.com/maps/place/data=!3m1!4b1!4m2!3m1!1s0x88540f0a39ec8997:0x1a37416f8c999eac",
            "cid": "1889050516061265580",
            "reviews_link": "https://search.google.com/local/reviews?placeid=ChIJl4nsOQoPVIgRrJ6ZjG9BNxo&q=bin+stores+in+north_carolina&authuser=0&hl=en&gl=US",
            "owner_id": "115124160294522878789",
            "owner_link": "https://maps.google.com/maps/contrib/115124160294522878789",
            "owner_name": "Where Ya Bin Concord",
            "booking_link": null,
            "reservations_link": null,
            "business_status": "OPEN",
            "type": "Store",
            "subtypes": [
                "Store"
            ],
            "photos_sample": [
                {
                    "photo_id": "AF1QipMJHOfH5S-ngg01IkCVQ5SzBGqjTGGf9p6UTbyj",
                    "photo_url": "https://lh5.googleusercontent.com/p/AF1QipMJHOfH5S-ngg01IkCVQ5SzBGqjTGGf9p6UTbyj",
                    "photo_url_large": "https://lh5.googleusercontent.com/p/AF1QipMJHOfH5S-ngg01IkCVQ5SzBGqjTGGf9p6UTbyj=w4000-h2252-k-no",
                    "video_thumbnail_url": null,
                    "latitude": 35.41979700270386,
                    "longitude": -80.57166332067166,
                    "type": "photo",
                    "photo_datetime_utc": "2023-03-03T00:00:00.000Z",
                    "photo_timestamp": 1677801600
                }
            ],
            "reviews_per_rating": null,
            "photo_count": 4,
            "about": {
                "summary": null,
                "details": {
                    "Service options": {
                        "Delivery": false,
                        "Same-day delivery": false
                    },
                    "Accessibility": {
                        "Wheelchair accessible entrance": true,
                        "Wheelchair accessible parking lot": true
                    },
                    "Payments": {
                        "Credit cards": true,
                        "Debit cards": true,
                        "NFC mobile payments": true
                    }
                }
            },
            "address": "30 Branchview Dr NE, Concord, NC 28025",
            "order_link": null,
            "price_level": null,
            "district": null,
            "street_address": "30 Branchview Dr NE",
            "city": "Concord",
            "zipcode": "28025",
            "state": "North Carolina",
            "country": "US",
            "emails_and_contacts": {
                "emails": [
                    "hr@whereyabinstores.com"
                ],
                "phone_numbers": [],
                "facebook": "https://www.facebook.com/whereyabinstores",
                "instagram": "https://www.instagram.com/whereyabinstore",
                "yelp": null,
                "tiktok": null,
                "snapchat": null,
                "twitter": null,
                "linkedin": "https://www.linkedin.com/company/where-ya-bin",
                "github": null,
                "youtube": null,
                "pinterest": null
            },
            "no": 84
        },
        {
            "business_id": "0x89ae87172195690b:0xb599e7141c23bff4",
            "google_id": "0x89ae87172195690b:0xb599e7141c23bff4",
            "place_id": "ChIJC2mVIReHrokR9L8jHBTnmbU",
            "google_mid": "/g/11rpc1r1m4",
            "phone_number": "+12522311092",
            "name": "DaaBIN Store - Rocky Mount, NC",
            "latitude": 35.929417199999996,
            "longitude": -77.7751893,
            "full_address": "DaaBIN Store - Rocky Mount, NC, 130 S Fairview Rd, Rocky Mount, NC 27801",
            "review_count": 95,
            "rating": 4.7,
            "timezone": "America/New_York",
            "opening_status": "Closed \u22c5 Opens 10\u202fAM Mon",
            "working_hours": {
                "Sunday": [
                    "Closed"
                ],
                "Monday": [
                    "10 AM\u20136 PM"
                ],
                "Tuesday": [
                    "10 AM\u20136 PM"
                ],
                "Wednesday": [
                    "10 AM\u20136 PM"
                ],
                "Thursday": [
                    "10 AM\u20136 PM"
                ],
                "Friday": [
                    "10 AM\u20136 PM"
                ],
                "Saturday": [
                    "10 AM\u20136 PM"
                ]
            },
            "website": "https://daabinstore.com/rocky-mount",
            "verified": true,
            "place_link": "https://www.google.com/maps/place/data=!3m1!4b1!4m2!3m1!1s0x89ae87172195690b:0xb599e7141c23bff4",
            "cid": "13085744265859153908",
            "reviews_link": "https://search.google.com/local/reviews?placeid=ChIJC2mVIReHrokR9L8jHBTnmbU&q=bin+stores+in+north_carolina&authuser=0&hl=en&gl=US",
            "owner_id": "111414060102329004529",
            "owner_link": "https://maps.google.com/maps/contrib/111414060102329004529",
            "owner_name": "DaaBIN Store - Rocky Mount, NC",
            "booking_link": null,
            "reservations_link": null,
            "business_status": "OPEN",
            "type": "Liquidator",
            "subtypes": [
                "Liquidator"
            ],
            "photos_sample": [
                {
                    "photo_id": "AF1QipMNy30LJy8bkD5Es0JJ4tdLSAZVh0NZZ7bt43uT",
                    "photo_url": "https://lh5.googleusercontent.com/p/AF1QipMNy30LJy8bkD5Es0JJ4tdLSAZVh0NZZ7bt43uT",
                    "photo_url_large": "https://lh5.googleusercontent.com/p/AF1QipMNy30LJy8bkD5Es0JJ4tdLSAZVh0NZZ7bt43uT=w4000-h3000-k-no",
                    "video_thumbnail_url": null,
                    "latitude": 35.9294259,
                    "longitude": -77.7747327,
                    "type": "photo",
                    "photo_datetime_utc": "2023-05-28T00:00:00.000Z",
                    "photo_timestamp": 1685232000
                }
            ],
            "reviews_per_rating": null,
            "photo_count": 4,
            "about": {
                "summary": null,
                "details": {
                    "Service options": {
                        "Onsite services": true
                    },
                    "Accessibility": {
                        "Wheelchair accessible entrance": true,
                        "Wheelchair accessible parking lot": true
                    }
                }
            },
            "address": "130 S Fairview Rd, Rocky Mount, NC 27801",
            "order_link": null,
            "price_level": null,
            "district": "Oakwood",
            "street_address": "130 S Fairview Rd",
            "city": "Rocky Mount",
            "zipcode": "27801",
            "state": "North Carolina",
            "country": "US",
            "emails_and_contacts": {
                "emails": [],
                "phone_numbers": [],
                "facebook": null,
                "instagram": null,
                "yelp": null,
                "tiktok": null,
                "snapchat": null,
                "twitter": null,
                "linkedin": null,
                "github": null,
                "youtube": null,
                "pinterest": null
            },
            "no": 84
        },
        {
            "business_id": "0x89ae7dfc9a84b6af:0x8eb8a860bb5158cd",
            "google_id": "0x89ae7dfc9a84b6af:0x8eb8a860bb5158cd",
            "place_id": "ChIJr7aEmvx9rokRzVhRu2CouI4",
            "google_mid": "/g/11rzcrmd0m",
            "phone_number": null,
            "name": "Bags and Bins",
            "latitude": 35.9739631,
            "longitude": -77.807064,
            "full_address": "Bags and Bins, 1100 N Wesleyan Blvd, Rocky Mount, NC 27804",
            "review_count": 55,
            "rating": 3.9,
            "timezone": "America/New_York",
            "opening_status": "Open \u22c5 Closes 5\u202fPM",
            "working_hours": {
                "Sunday": [
                    "12\u20135 PM"
                ],
                "Monday": [
                    "10 AM\u20135 PM"
                ],
                "Tuesday": [
                    "10 AM\u20135 PM"
                ],
                "Wednesday": [
                    "10 AM\u20132 PM"
                ],
                "Thursday": [
                    "Closed"
                ],
                "Friday": [
                    "Closed"
                ],
                "Saturday": [
                    "9 AM\u20136 PM"
                ]
            },
            "website": "http://www.facebook.com/bagsandbinsrockymount",
            "verified": true,
            "place_link": "https://www.google.com/maps/place/data=!3m1!4b1!4m2!3m1!1s0x89ae7dfc9a84b6af:0x8eb8a860bb5158cd",
            "cid": "10284154882513524941",
            "reviews_link": "https://search.google.com/local/reviews?placeid=ChIJr7aEmvx9rokRzVhRu2CouI4&q=bin+stores+in+north_carolina&authuser=0&hl=en&gl=US",
            "owner_id": "111979841341751243514",
            "owner_link": "https://maps.google.com/maps/contrib/111979841341751243514",
            "owner_name": "Bags and Bins",
            "booking_link": null,
            "reservations_link": null,
            "business_status": "OPEN",
            "type": "Discount store",
            "subtypes": [
                "Discount store"
            ],
            "photos_sample": [
                {
                    "photo_id": "AF1QipMd8nQ4Qh-bE2ApcRwdaegX05U661VwzofPf0_C",
                    "photo_url": "https://lh5.googleusercontent.com/p/AF1QipMd8nQ4Qh-bE2ApcRwdaegX05U661VwzofPf0_C",
                    "photo_url_large": "https://lh5.googleusercontent.com/p/AF1QipMd8nQ4Qh-bE2ApcRwdaegX05U661VwzofPf0_C=w2160-h2160-k-no",
                    "video_thumbnail_url": null,
                    "latitude": 35.9733442,
                    "longitude": -77.8066551,
                    "type": "photo",
                    "photo_datetime_utc": "2022-06-07T00:00:00.000Z",
                    "photo_timestamp": 1654560000
                }
            ],
            "reviews_per_rating": null,
            "photo_count": 4,
            "about": {
                "summary": null,
                "details": {
                    "From the business": {
                        "Small business": true
                    },
                    "Service options": {
                        "In-store shopping": true,
                        "Delivery": false,
                        "Same-day delivery": false
                    },
                    "Accessibility": {
                        "Wheelchair accessible entrance": true,
                        "Wheelchair accessible parking lot": true
                    },
                    "Payments": {
                        "Credit cards": true,
                        "Debit cards": true
                    }
                }
            },
            "address": "1100 N Wesleyan Blvd, Rocky Mount, NC 27804",
            "order_link": null,
            "price_level": null,
            "district": "Golden East",
            "street_address": "1100 N Wesleyan Blvd",
            "city": "Rocky Mount",
            "zipcode": "27804",
            "state": "North Carolina",
            "country": "US",
            "emails_and_contacts": {
                "emails": [],
                "phone_numbers": [],
                "facebook": null,
                "instagram": null,
                "yelp": null,
                "tiktok": null,
                "snapchat": null,
                "twitter": null,
                "linkedin": null,
                "github": null,
                "youtube": null,
                "pinterest": null
            },
            "no": 84
        },
        {
            "business_id": "0x88532bd5eaf2387f:0x73e6ef1be24bfda0",
            "google_id": "0x88532bd5eaf2387f:0x73e6ef1be24bfda0",
            "place_id": "ChIJfzjy6tUrU4gRoP1L4hvv5nM",
            "google_mid": "/g/11trtpg6q9",
            "phone_number": "+13362705281",
            "name": "DaaBIN Store - Graham, NC",
            "latitude": 36.056722199999996,
            "longitude": -79.40117,
            "full_address": "DaaBIN Store - Graham, NC, 811 S Main St, Graham, NC 27253",
            "review_count": 68,
            "rating": 4.4,
            "timezone": "America/New_York",
            "opening_status": "Open \u22c5 Closes 5\u202fPM",
            "working_hours": {
                "Sunday": [
                    "12\u20135 PM"
                ],
                "Monday": [
                    "9 AM\u20135 PM"
                ],
                "Tuesday": [
                    "9 AM\u20135 PM"
                ],
                "Wednesday": [
                    "9 AM\u201312 PM"
                ],
                "Thursday": [
                    "Closed"
                ],
                "Friday": [
                    "Closed"
                ],
                "Saturday": [
                    "9 AM\u20135 PM"
                ]
            },
            "website": "https://daabinstore.com/graham",
            "verified": true,
            "place_link": "https://www.google.com/maps/place/data=!3m1!4b1!4m2!3m1!1s0x88532bd5eaf2387f:0x73e6ef1be24bfda0",
            "cid": "8351625462044949920",
            "reviews_link": "https://search.google.com/local/reviews?placeid=ChIJfzjy6tUrU4gRoP1L4hvv5nM&q=bin+stores+in+north_carolina&authuser=0&hl=en&gl=US",
            "owner_id": "105890981885625561870",
            "owner_link": "https://maps.google.com/maps/contrib/105890981885625561870",
            "owner_name": "DaaBIN Store - Graham, NC",
            "booking_link": null,
            "reservations_link": null,
            "business_status": "OPEN",
            "type": "Discount store",
            "subtypes": [
                "Discount store"
            ],
            "photos_sample": [
                {
                    "photo_id": "AF1QipOLPJvDSF2_BaAw4My--zDFYjpmpWNLpJRHlZYv",
                    "photo_url": "https://lh5.googleusercontent.com/p/AF1QipOLPJvDSF2_BaAw4My--zDFYjpmpWNLpJRHlZYv",
                    "photo_url_large": "https://lh5.googleusercontent.com/p/AF1QipOLPJvDSF2_BaAw4My--zDFYjpmpWNLpJRHlZYv=w4032-h3024-k-no",
                    "video_thumbnail_url": null,
                    "latitude": 36.056668099999996,
                    "longitude": -79.4009597,
                    "type": "photo",
                    "photo_datetime_utc": "2023-05-28T00:00:00.000Z",
                    "photo_timestamp": 1685232000
                }
            ],
            "reviews_per_rating": null,
            "photo_count": 4,
            "about": {
                "summary": null,
                "details": {
                    "Service options": {
                        "Onsite services": true,
                        "Delivery": false,
                        "Same-day delivery": false
                    },
                    "Accessibility": {
                        "Wheelchair accessible entrance": true,
                        "Wheelchair accessible parking lot": true
                    },
                    "Planning": {
                        "Quick visit": true
                    },
                    "Payments": {
                        "Credit cards": true,
                        "Debit cards": true
                    }
                }
            },
            "address": "811 S Main St, Graham, NC 27253",
            "order_link": null,
            "price_level": null,
            "district": null,
            "street_address": "811 S Main St",
            "city": "Graham",
            "zipcode": "27253",
            "state": "North Carolina",
            "country": "US",
            "emails_and_contacts": {
                "emails": [],
                "phone_numbers": [],
                "facebook": null,
                "instagram": null,
                "yelp": null,
                "tiktok": null,
                "snapchat": null,
                "twitter": null,
                "linkedin": null,
                "github": null,
                "youtube": null,
                "pinterest": null
            },
            "no": 84
        },
        {
            "business_id": "0x89a8d197d02d54d3:0xef4c84e41350ed",
            "google_id": "0x89a8d197d02d54d3:0xef4c84e41350ed",
            "place_id": "ChIJ01Qt0JfRqIkR7VAT5IRM7wA",
            "google_mid": "/g/11y30zspwb",
            "phone_number": "+12526311477",
            "name": "Bear Bins",
            "latitude": 35.0820904,
            "longitude": -77.0332829,
            "full_address": "Bear Bins, 955 US-70, New Bern, NC 28560",
            "review_count": 12,
            "rating": 4.7,
            "timezone": "America/New_York",
            "opening_status": "Open \u22c5 Closes 5\u202fPM",
            "working_hours": {
                "Sunday": [
                    "12\u20135 PM"
                ],
                "Monday": [
                    "10 AM\u20136 PM"
                ],
                "Tuesday": [
                    "10 AM\u20136 PM"
                ],
                "Wednesday": [
                    "10 AM\u20136 PM"
                ],
                "Thursday": [
                    "10 AM\u20136 PM"
                ],
                "Friday": [
                    "Closed"
                ],
                "Saturday": [
                    "10 AM\u20136 PM"
                ]
            },
            "website": "https://www.facebook.com/profile.php?id=61554835260687",
            "verified": true,
            "place_link": "https://www.google.com/maps/place/data=!3m1!4b1!4m2!3m1!1s0x89a8d197d02d54d3:0xef4c84e41350ed",
            "cid": "67356653079711981",
            "reviews_link": "https://search.google.com/local/reviews?placeid=ChIJ01Qt0JfRqIkR7VAT5IRM7wA&q=bin+stores+in+north_carolina&authuser=0&hl=en&gl=US",
            "owner_id": "113753322439723973069",
            "owner_link": "https://maps.google.com/maps/contrib/113753322439723973069",
            "owner_name": "Bear Bins",
            "booking_link": null,
            "reservations_link": null,
            "business_status": "OPEN",
            "type": "Discount store",
            "subtypes": [
                "Discount store"
            ],
            "photos_sample": [
                {
                    "photo_id": "AF1QipNiSadlytzL30vCmWNa-IaTCFPjlJ3zEUNV_ZMk",
                    "photo_url": "https://lh5.googleusercontent.com/p/AF1QipNiSadlytzL30vCmWNa-IaTCFPjlJ3zEUNV_ZMk",
                    "photo_url_large": "https://lh5.googleusercontent.com/p/AF1QipNiSadlytzL30vCmWNa-IaTCFPjlJ3zEUNV_ZMk=w1080-h1920-k-no",
                    "video_thumbnail_url": null,
                    "latitude": 35.082090380521656,
                    "longitude": -77.03328286152116,
                    "type": "photo",
                    "photo_datetime_utc": "2024-03-14T00:00:00.000Z",
                    "photo_timestamp": 1710374400
                }
            ],
            "reviews_per_rating": null,
            "photo_count": 4,
            "about": {
                "summary": null,
                "details": {
                    "From the business": {
                        "Identifies as women-owned": true,
                        "Small business": true
                    },
                    "Service options": {
                        "Delivery": false,
                        "Same-day delivery": false
                    },
                    "Accessibility": {
                        "Wheelchair accessible entrance": true,
                        "Wheelchair accessible parking lot": true
                    },
                    "Payments": {
                        "Credit cards": true
                    }
                }
            },
            "address": "955 US-70, New Bern, NC 28560",
            "order_link": null,
            "price_level": null,
            "district": null,
            "street_address": "955 US-70",
            "city": "New Bern",
            "zipcode": "28560",
            "state": "North Carolina",
            "country": "US",
            "emails_and_contacts": {
                "emails": [],
                "phone_numbers": [],
                "facebook": null,
                "instagram": null,
                "yelp": null,
                "tiktok": null,
                "snapchat": null,
                "twitter": null,
                "linkedin": null,
                "github": null,
                "youtube": null,
                "pinterest": null
            },
            "no": 84
        },
        {
            "business_id": "0x88512f8f4da45519:0x92135ca0b9b9d888",
            "google_id": "0x88512f8f4da45519:0x92135ca0b9b9d888",
            "place_id": "ChIJGVWkTY8vUYgRiNi5uaBcE5I",
            "google_mid": "/g/11qnt74bpn",
            "phone_number": "+18282163108",
            "name": "One Stop Bargains",
            "latitude": 35.7399821,
            "longitude": -81.3654554,
            "full_address": "One Stop Bargains, 538 US-321, Hickory, NC 28601",
            "review_count": 71,
            "rating": 4.2,
            "timezone": "America/New_York",
            "opening_status": "Open \u22c5 Closes 6\u202fPM",
            "working_hours": {
                "Sunday": [
                    "12\u20136 PM"
                ],
                "Monday": [
                    "10 AM\u20136 PM"
                ],
                "Tuesday": [
                    "10 AM\u20136 PM"
                ],
                "Wednesday": [
                    "10 AM\u20136 PM"
                ],
                "Thursday": [
                    "10 AM\u20136 PM"
                ],
                "Friday": [
                    "10 AM\u20136 PM"
                ],
                "Saturday": [
                    "10 AM\u20136 PM"
                ]
            },
            "website": null,
            "verified": true,
            "place_link": "https://www.google.com/maps/place/data=!3m1!4b1!4m2!3m1!1s0x88512f8f4da45519:0x92135ca0b9b9d888",
            "cid": "10525858599475468424",
            "reviews_link": "https://search.google.com/local/reviews?placeid=ChIJGVWkTY8vUYgRiNi5uaBcE5I&q=bin+stores+in+north_carolina&authuser=0&hl=en&gl=US",
            "owner_id": "101740152108026098039",
            "owner_link": "https://maps.google.com/maps/contrib/101740152108026098039",
            "owner_name": "One Stop Bargains",
            "booking_link": null,
            "reservations_link": null,
            "business_status": "OPEN",
            "type": "Discount store",
            "subtypes": [
                "Discount store"
            ],
            "photos_sample": [
                {
                    "photo_id": "AF1QipOEAAQLoMOGBLJz19zkQPvW3r0iP-bonveArH4w",
                    "photo_url": "https://lh5.googleusercontent.com/p/AF1QipOEAAQLoMOGBLJz19zkQPvW3r0iP-bonveArH4w",
                    "photo_url_large": "https://lh5.googleusercontent.com/p/AF1QipOEAAQLoMOGBLJz19zkQPvW3r0iP-bonveArH4w=w3024-h4032-k-no",
                    "video_thumbnail_url": null,
                    "latitude": 35.740014099999996,
                    "longitude": -81.36585649999999,
                    "type": "photo",
                    "photo_datetime_utc": "2021-03-16T00:00:00.000Z",
                    "photo_timestamp": 1615852800
                }
            ],
            "reviews_per_rating": null,
            "photo_count": 88,
            "about": {
                "summary": null,
                "details": {
                    "From the business": {
                        "Small business": true
                    },
                    "Service options": {
                        "Delivery": false,
                        "Same-day delivery": false
                    },
                    "Accessibility": {
                        "Wheelchair accessible entrance": true,
                        "Wheelchair accessible parking lot": true
                    },
                    "Planning": {
                        "Quick visit": true
                    },
                    "Payments": {
                        "Credit cards": true,
                        "Debit cards": true,
                        "NFC mobile payments": true
                    }
                }
            },
            "address": "538 US-321, Hickory, NC 28601",
            "order_link": null,
            "price_level": null,
            "district": null,
            "street_address": "538 US-321",
            "city": "Hickory",
            "zipcode": "28601",
            "state": "North Carolina",
            "country": "US",
            "emails_and_contacts": {
                "emails": [],
                "phone_numbers": [],
                "facebook": null,
                "instagram": null,
                "yelp": null,
                "tiktok": null,
                "snapchat": null,
                "twitter": null,
                "linkedin": null,
                "github": null,
                "youtube": null,
                "pinterest": null
            },
            "no": 84
        },
        {
            "business_id": "0x89a8c15d2ee2c19f:0xf8485aad94526b17",
            "google_id": "0x89a8c15d2ee2c19f:0xf8485aad94526b17",
            "place_id": "ChIJn8HiLl3BqIkRF2tSlK1aSPg",
            "google_mid": "/g/11kj_w0fcb",
            "phone_number": "+12526526437",
            "name": "Bargain Binz ENC",
            "latitude": 34.880615899999995,
            "longitude": -76.90591739999999,
            "full_address": "Bargain Binz ENC, 215 E Main St, Havelock, NC 28532",
            "review_count": 40,
            "rating": 4.4,
            "timezone": "America/New_York",
            "opening_status": "Closed \u22c5 Opens 9\u202fAM Mon",
            "working_hours": {
                "Sunday": [
                    "Closed"
                ],
                "Monday": [
                    "9 AM\u20136 PM"
                ],
                "Tuesday": [
                    "9 AM\u20136 PM"
                ],
                "Wednesday": [
                    "9 AM\u20136 PM"
                ],
                "Thursday": [
                    "Closed"
                ],
                "Friday": [
                    "9 AM\u20136 PM"
                ],
                "Saturday": [
                    "9 AM\u20136 PM"
                ]
            },
            "website": "https://www.facebook.com/profile.php?id=100091066240339&mibextid=LQQJ4d",
            "verified": true,
            "place_link": "https://www.google.com/maps/place/data=!3m1!4b1!4m2!3m1!1s0x89a8c15d2ee2c19f:0xf8485aad94526b17",
            "cid": "17890649221293566743",
            "reviews_link": "https://search.google.com/local/reviews?placeid=ChIJn8HiLl3BqIkRF2tSlK1aSPg&q=bin+stores+in+north_carolina&authuser=0&hl=en&gl=US",
            "owner_id": "111229515239856211241",
            "owner_link": "https://maps.google.com/maps/contrib/111229515239856211241",
            "owner_name": "Bargain Binz ENC",
            "booking_link": null,
            "reservations_link": null,
            "business_status": "OPEN",
            "type": "Discount store",
            "subtypes": [
                "Discount store"
            ],
            "photos_sample": [
                {
                    "photo_id": "AF1QipNruZzMS_BYAhyAKfKgTl6eNElSKtrG3p5xwfjp",
                    "photo_url": "https://lh5.googleusercontent.com/p/AF1QipNruZzMS_BYAhyAKfKgTl6eNElSKtrG3p5xwfjp",
                    "photo_url_large": "https://lh5.googleusercontent.com/p/AF1QipNruZzMS_BYAhyAKfKgTl6eNElSKtrG3p5xwfjp=w3024-h4032-k-no",
                    "video_thumbnail_url": null,
                    "latitude": 34.8807456,
                    "longitude": -76.9059621,
                    "type": "photo",
                    "photo_datetime_utc": "2023-05-30T00:00:00.000Z",
                    "photo_timestamp": 1685404800
                }
            ],
            "reviews_per_rating": null,
            "photo_count": 4,
            "about": {
                "summary": null,
                "details": {
                    "Service options": {
                        "Delivery": false,
                        "Same-day delivery": false
                    },
                    "Accessibility": {
                        "Wheelchair accessible entrance": true,
                        "Wheelchair accessible parking lot": true
                    },
                    "Payments": {
                        "Credit cards": true
                    }
                }
            },
            "address": "215 E Main St, Havelock, NC 28532",
            "order_link": null,
            "price_level": null,
            "district": null,
            "street_address": "215 E Main St",
            "city": "Havelock",
            "zipcode": "28532",
            "state": "North Carolina",
            "country": "US",
            "emails_and_contacts": {
                "emails": [],
                "phone_numbers": [],
                "facebook": null,
                "instagram": null,
                "yelp": null,
                "tiktok": null,
                "snapchat": null,
                "twitter": null,
                "linkedin": null,
                "github": null,
                "youtube": null,
                "pinterest": null
            },
            "no": 84
        },
        {
            "business_id": "0x89ac5dce13c64ea1:0x99bf4d291e947f36",
            "google_id": "0x89ac5dce13c64ea1:0x99bf4d291e947f36",
            "place_id": "ChIJoU7GE85drIkRNn-UHilNv5k",
            "google_mid": "/g/11sb3q0dst",
            "phone_number": "+14348064643",
            "name": "ToteBoys Bin Store",
            "latitude": 35.7985758,
            "longitude": -78.5586249,
            "full_address": "ToteBoys Bin Store, 4531 New Bern Ave #160, Raleigh, NC 27610",
            "review_count": 23,
            "rating": 4.5,
            "timezone": "America/New_York",
            "opening_status": "Open \u22c5 Closes 6\u202fPM",
            "working_hours": {
                "Sunday": [
                    "10 AM\u20136 PM"
                ],
                "Monday": [
                    "10 AM\u20136 PM"
                ],
                "Tuesday": [
                    "Closed"
                ],
                "Wednesday": [
                    "10 AM\u20136 PM"
                ],
                "Thursday": [
                    "10 AM\u20136 PM"
                ],
                "Friday": [
                    "10 AM\u20136 PM"
                ],
                "Saturday": [
                    "10 AM\u20136 PM"
                ]
            },
            "website": "http://www.toteboys.com",
            "verified": true,
            "place_link": "https://www.google.com/maps/place/data=!3m1!4b1!4m2!3m1!1s0x89ac5dce13c64ea1:0x99bf4d291e947f36",
            "cid": "11078658447356755766",
            "reviews_link": "https://search.google.com/local/reviews?placeid=ChIJoU7GE85drIkRNn-UHilNv5k&q=bin+stores+in+north_carolina&authuser=0&hl=en&gl=US",
            "owner_id": "105037719374948825498",
            "owner_link": "https://maps.google.com/maps/contrib/105037719374948825498",
            "owner_name": "ToteBoys Bin Store",
            "booking_link": null,
            "reservations_link": null,
            "business_status": "OPEN",
            "type": "Discount store",
            "subtypes": [
                "Discount store"
            ],
            "photos_sample": [
                {
                    "photo_id": "AF1QipMlAGcR8yjfv_NXhxgL7nhq7AKTdJbfc60t3vkm",
                    "photo_url": "https://lh5.googleusercontent.com/p/AF1QipMlAGcR8yjfv_NXhxgL7nhq7AKTdJbfc60t3vkm",
                    "photo_url_large": "https://lh5.googleusercontent.com/p/AF1QipMlAGcR8yjfv_NXhxgL7nhq7AKTdJbfc60t3vkm=w4000-h3000-k-no",
                    "video_thumbnail_url": null,
                    "latitude": 35.798648299999996,
                    "longitude": -78.5589076,
                    "type": "photo",
                    "photo_datetime_utc": "2022-11-30T00:00:00.000Z",
                    "photo_timestamp": 1669766400
                }
            ],
            "reviews_per_rating": null,
            "photo_count": 3,
            "about": {
                "summary": null,
                "details": {
                    "Service options": {
                        "Delivery": false,
                        "Same-day delivery": false
                    },
                    "Accessibility": {
                        "Wheelchair accessible entrance": true,
                        "Wheelchair accessible parking lot": true
                    },
                    "Payments": {
                        "Credit cards": true,
                        "Debit cards": true,
                        "NFC mobile payments": true
                    }
                }
            },
            "address": "4531 New Bern Ave #160, Raleigh, NC 27610",
            "order_link": null,
            "price_level": null,
            "district": "Northeast Raleigh",
            "street_address": "4531 New Bern Ave #160",
            "city": "Raleigh",
            "zipcode": "27610",
            "state": "North Carolina",
            "country": "US",
            "emails_and_contacts": {
                "emails": [],
                "phone_numbers": [
                    "9292426868"
                ],
                "facebook": "https://www.facebook.com/fbtoteboys",
                "instagram": "https://www.instagram.com/toteboys",
                "yelp": null,
                "tiktok": null,
                "snapchat": null,
                "twitter": null,
                "linkedin": null,
                "github": null,
                "youtube": null,
                "pinterest": null
            },
            "no": 84
        },
        {
            "business_id": "0x88542393a1459ba3:0xa919fa6ca0abe25c",
            "google_id": "0x88542393a1459ba3:0xa919fa6ca0abe25c",
            "place_id": "ChIJo5tFoZMjVIgRXOKroGz6Gak",
            "google_mid": "/g/11k5255p_q",
            "phone_number": null,
            "name": "Where Ya Bin Matthews",
            "latitude": 35.12195,
            "longitude": -80.70653,
            "full_address": "Where Ya Bin Matthews, 1834 Matthews Township Pkwy #100, Matthews, NC 28105",
            "review_count": 254,
            "rating": 3.8,
            "timezone": "America/New_York",
            "opening_status": "Open \u22c5 Closes 7\u202fPM",
            "working_hours": {
                "Sunday": [
                    "9 AM\u20137 PM"
                ],
                "Monday": [
                    "9 AM\u20138 PM"
                ],
                "Tuesday": [
                    "9 AM\u20138 PM"
                ],
                "Wednesday": [
                    "9 AM\u20138 PM"
                ],
                "Thursday": [
                    "9 AM\u20134 PM"
                ],
                "Friday": [
                    "8 AM\u20138 PM"
                ],
                "Saturday": [
                    "9 AM\u20138 PM"
                ]
            },
            "website": "http://www.whereyabinstores.com",
            "verified": true,
            "place_link": "https://www.google.com/maps/place/data=!3m1!4b1!4m2!3m1!1s0x88542393a1459ba3:0xa919fa6ca0abe25c",
            "cid": "12185045611286618716",
            "reviews_link": "https://search.google.com/local/reviews?placeid=ChIJo5tFoZMjVIgRXOKroGz6Gak&q=bin+stores+in+north_carolina&authuser=0&hl=en&gl=US",
            "owner_id": "106701388874024877518",
            "owner_link": "https://maps.google.com/maps/contrib/106701388874024877518",
            "owner_name": "Where Ya Bin Matthews",
            "booking_link": null,
            "reservations_link": null,
            "business_status": "OPEN",
            "type": "Discount store",
            "subtypes": [
                "Discount store",
                "General store"
            ],
            "photos_sample": [
                {
                    "photo_id": "AF1QipOwK9TEnYdd6WVbKBcTqYwmkjqxbpQMNa5HVbbZ",
                    "photo_url": "https://lh5.googleusercontent.com/p/AF1QipOwK9TEnYdd6WVbKBcTqYwmkjqxbpQMNa5HVbbZ",
                    "photo_url_large": "https://lh5.googleusercontent.com/p/AF1QipOwK9TEnYdd6WVbKBcTqYwmkjqxbpQMNa5HVbbZ=w4000-h2252-k-no",
                    "video_thumbnail_url": null,
                    "latitude": 35.1222961,
                    "longitude": -80.70675159999999,
                    "type": "photo",
                    "photo_datetime_utc": "2023-03-01T00:00:00.000Z",
                    "photo_timestamp": 1677628800
                }
            ],
            "reviews_per_rating": null,
            "photo_count": 67,
            "about": {
                "summary": null,
                "details": {
                    "Service options": {
                        "Onsite services": true,
                        "Delivery": false,
                        "Same-day delivery": false
                    },
                    "Accessibility": {
                        "Wheelchair accessible entrance": true,
                        "Wheelchair accessible parking lot": true
                    },
                    "Payments": {
                        "Credit cards": true,
                        "Debit cards": true,
                        "NFC mobile payments": true
                    }
                }
            },
            "address": "1834 Matthews Township Pkwy #100, Matthews, NC 28105",
            "order_link": null,
            "price_level": null,
            "district": null,
            "street_address": "1834 Matthews Township Pkwy #100",
            "city": "Matthews",
            "zipcode": "28105",
            "state": "North Carolina",
            "country": "US",
            "emails_and_contacts": {
                "emails": [
                    "hr@whereyabinstores.com"
                ],
                "phone_numbers": [],
                "facebook": "https://www.facebook.com/whereyabinstores",
                "instagram": "https://www.instagram.com/whereyabinstore",
                "yelp": "https://www.yelp.com/biz/where-ya-bin-matthews",
                "tiktok": null,
                "snapchat": null,
                "twitter": null,
                "linkedin": "https://www.linkedin.com/company/where-ya-bin",
                "github": null,
                "youtube": null,
                "pinterest": null
            },
            "no": 84
        }
    ]
}